Workbook

Sheet Key Stats
A5: Apple Inc. (NasdaqGS:AAPL) > Financials > Key Stats
A7: In Millions of the trading currency, except per share items. | B7: Currency: | C7: Trading Currency | E7: Conversion: | F7: Historical
B8: Order: | C8: Latest on Right | E8: Units: | F8: S&P Capital IQ (Default)
B9: Decimals: | C9: Capital IQ (Default) | E9: Dilution: | F9: Basic
A12: Key Financials¹
A13: For the Fiscal Period Ending | B13: 12 months Sep-28-2013A | C13: 12 months Sep-27-2014A | D13: 12 months Sep-26-2015A | E13: 12 months Sep-24-2016A | F13: 12 months Sep-30-2017A | G13: 12 months Sep-29-2018A | H13: 12 months Sep-28-2019A | I13: 12 months Sep-26-2020A | J13: 12 months Sep-25-2021A | K13: 12 months Sep-24-2022A | L13: 12 months Sep-30-2023A | M13: LTM² 12 months Dec-30-2023A | N13: 12 months† Sep-30-2024E | O13: 12 months Sep-30-2025E | P13: 12 months Sep-30-2026E
A14: Currency | B14: USD | C14: USD | D14: USD | E14: USD | F14: USD | G14: USD | H14: USD | I14: USD | J14: USD | K14: USD | L14: USD | M14: USD | N14: USD | O14: USD | P14: USD
A16: Total Revenue | B16: 170910 | C16: 182795 | D16: 233715 | E16: 215639 | F16: 229234 | G16: 265595 | H16: 260174 | I16: 274515 | J16: 365817 | K16: 394328 | L16: 383285 | M16: 385706 | N16: 388204.69 | O16: 412561.7 | P16: 435593.04
A17: Growth Over Prior Year | B17: 0.09202 | C17: 0.069539 | D17: 0.278563 | E17: -0.077343 | F17: 0.063045 | G17: 0.158619 | H17: -0.020411 | I17: 0.05512 | J17: 0.332593 | K17: 0.077937 | L17: -0.028005 | M17: -0.004725 | N17: 0.012835605 | O17: 0.062742677 | P17: 0.055825209
A19: Gross Profit | B19: 64304 | C19: 70537 | D19: 93626 | E19: 84263 | F19: 88186 | G19: 101839 | H19: 98392 | I19: 104956 | J19: 152836 | K19: 170782 | L19: 169148 | M19: 173671 | N19: - | O19: - | P19: -
A20: Margin % | B20: 0.376244 | C20: 0.38588 | D20: 0.400599 | E20: 0.390759 | F20: 0.384698 | G20: 0.383437 | H20: 0.378177 | I20: 0.382332 | J20: 0.417793 | K20: 0.433096 | L20: 0.441311 | M20: 0.450267 | N20: 0.458179 | O20: 0.458491 | P20: 0.4585781
A22: EBITDA | B22: 55756 | C22: 60449 | D22: 82487 | E22: 70529 | F22: 71501 | G22: 81801 | H22: 76477 | I22: 77344 | J22: 120233 | K22: 130541 | L22: 125820 | M22: 130109 | N22: 132236.37 | O22: 141059.85 | P22: 148981.06
A23: Margin % | B23: 0.32623 | C23: 0.330692 | D23: 0.352938 | E23: 0.327069 | F23: 0.311912 | G23: 0.307991 | H23: 0.293945 | I23: 0.281747 | J23: 0.328669 | K23: 0.331046 | L23: 0.328267 | M23: 0.337326 | N23: 0.34063568 | O23: 0.34191214 | P23: 0.34201892
A25: EBIT | B25: 48999 | C25: 52503 | D25: 71230 | E25: 60024 | F25: 61344 | G25: 70898 | H25: 63930 | I25: 66288 | J25: 108949 | K25: 119437 | L25: 114301 | M25: 118658 | N25: 120143.29 | O25: 127664.82 | P25: 135528.9
A26: Margin % | B26: 0.286694 | C26: 0.287223 | D26: 0.304772 | E26: 0.278354 | F26: 0.267604 | G26: 0.26694 | H26: 0.24572 | I26: 0.241473 | J26: 0.297823 | K26: 0.302887 | L26: 0.298214 | M26: 0.307638 | N26: 0.30948437 | O26: 0.3094442 | P26: 0.31113652
A28: Earnings from Cont. Ops. | B28: 37037 | C28: 39510 | D28: 53394 | E28: 45687 | F28: 48351 | G28: 59531 | H28: 55256 | I28: 57411 | J28: 94680 | K28: 99803 | L28: 96995 | M28: 100913 | N28: - | O28: - | P28: -
A29: Margin % | B29: 0.216704 | C29: 0.216143 | D29: 0.228457 | E29: 0.211867 | F29: 0.210924 | G29: 0.224142 | H29: 0.21238 | I29: 0.209136 | J29: 0.258817 | K29: 0.253096 | L29: 0.253062 | M29: 0.261631 | N29: - | O29: - | P29: -
A31: Net Income | B31: 37037 | C31: 39510 | D31: 53394 | E31: 45687 | F31: 48351 | G31: 59531 | H31: 55256 | I31: 57411 | J31: 94680 | K31: 99803 | L31: 96995 | M31: 100913 | N31: 100916.95 | O31: 107037.47 | P31: 114247.86
A32: Margin % | B32: 0.216704 | C32: 0.216143 | D32: 0.228457 | E32: 0.211867 | F32: 0.210924 | G32: 0.224142 | H32: 0.21238 | I32: 0.209136 | J32: 0.258817 | K32: 0.253096 | L32: 0.253062 | M32: 0.261631 | N32: 0.25995808 | O32: 0.25944597 | P32: 0.2622812
A34: Diluted EPS Excl. Extra Items³ | B34: 1.42 | C34: 1.6125 | D34: 2.305 | E34: 2.0775 | F34: 2.3025 | G34: 2.98 | H34: 2.97 | I34: 3.28 | J34: 5.61 | K34: 6.11 | L34: 6.13 | M34: 6.418925 | N34: 6.56319 | O34: 7.16097 | P34: 7.78477
A35: Growth Over Prior Year | B35: -0.099842 | C35: 0.135563 | D35: 0.429457 | E35: -0.098699 | F35: 0.108303 | G35: 0.294245 | H35: -0.003356 | I35: 0.104377 | J35: 0.710365 | K35: 0.089126 | L35: 0.003273 | M35: 0.092921 | N35: 0.07066721 | O35: 0.091080709 | P35: 0.087111104
A38: Currency | B38: USD | C38: USD | D38: USD | E38: USD | F38: USD | G38: USD | H38: USD | I38: USD | J38: USD | K38: USD | L38: USD | M38: USD | N38: USD | O38: USD | P38: USD
A39: Exchange Rate | B39: 1 | C39: 1 | D39: 1 | E39: 1 | F39: 1 | G39: 1 | H39: 1 | I39: 1 | J39: 1 | K39: 1 | L39: 1 | M39: 1 | N39: 1 | O39: 1 | P39: 1
A40: Conversion Method | B40: H | C40: H | D40: H | E40: H | F40: H | G40: H | H40: H | I40: H | J40: H | K40: H | L40: H | M40: H | N40: S | O40: S | P40: S
A42: ¹All results are taken from the most recently filed statement for each period. When there has been more than one, earlier filings can be viewed on the individual statement pages.
A43: ²Growth rates for the LTM period are calculated against the LTM period ending 12 months before.
A44: ³All forward period figures are consensus mean estimates provided by the brokers and may not be on a comparable basis as financials.
A45: †Growth rates for forward periods are calculated against prior period estimates or actual pro forma results as disclosed on the Estimates Consensus page.
A46: Growth Rates are calculated in originally reported currency only and will not reflect any currency conversion selected above.
A48: Current Capitalization (Millions of USD)
A49: Currency | B49: USD
A50: Share Price | B50: 172.62
A51: Shares Out. | B51: 15441.881
A53: Market Capitalization | B53: 2665577.5
A54: - Cash & Short Term Investments | B54: 73100
A55: + Total Debt | B55: 108040
A56: + Pref. Equity | B56: -
A57: + Total Minority Interest | B57: -
A58: - Long Term Marketable Securities | B58: 99475
A59: = Total Enterprise Value (TEV) | B59: 2601042.5
A61: Book Value of Common Equity | B61: 74100
A62: + Pref. Equity | B62: -
A63: + Total Minority Interest | B63: -
A64: + Total Debt | B64: 108040
A65: = Total Capital | B65: 182140
A67: **For companies that have multiple share classes that publicly trade, we are incorporating the different prices to calculate our company level market capitalization. Please click on the value to see the detailed calculation. Prices shown on this page are the close price of the company’s primary stock class. Shares shown on this page are total company as-reported share values.
A71: Total Liability includes Total Debt, Minority Interest and Pref. Equity.
A72: Net Liability includes Total Liability, net of Cash and Short Term Investments.
A73: TEV includes Market Cap and Net Liability.
A74: Total Capital includes Common Equity and Total Liability.
A76: Valuation Multiples based on Current Capitalization
A77: For the Fiscal Period Ending | B77: 12 months Sep-30-2023A | C77: LTM 12 months Dec-30-2023A | D77: 12 months Sep-30-2024E | E77: 12 months Sep-30-2025E | F77: 12 months Sep-30-2026E
A78: TEV/Total Revenue | B78: 6.854973 | C78: 6.743588 | D78: 6.700183 | E78: 6.3046146 | F78: 5.9712674
A80: TEV/EBITDA | B80: 18.539433 | C80: 17.814261 | D80: 19.669645 | E80: 18.439283 | F80: 17.45888
A82: TEV/EBIT | B82: 22.986749 | C82: 21.920498 | D82: 21.649503 | E82: 20.373995 | F82: 19.191792
A84: P/Diluted EPS Before Extra | B84: 28.159869 | C84: 26.892353 | D84: 26.301235 | E84: 24.105673 | F84: 22.174066
A86: P/BV | B86: 43.192674 | C86: 36.015435 | D86: 35.972317 | E86: 32.472272 | F86: 24.270186
A88: Price/Tang BV | B88: 43.192674 | C88: 36.015435 | D88: - | E88: - | F88: -
A91: Last Year's Return | B91: Asj. Closing
A92: 44925 | B92: 129.04
A93: 45289 | B93: 192.28
A94: Return | B94: =B93/B92-1 -> 0.4900806

Sheet IS
A5: Apple Inc. (NasdaqGS:AAPL) > Financials > Income Statement
A7: In Millions of the reported currency, except per share items. | B7: Template: | C7: Standard | E7: Restatement: | F7: Latest Filings
B8: Period Type: | C8: Annual | E8: Order: | F8: Latest on Right
B9: Currency: | C9: Reported Currency | E9: Conversion: | F9: Historical
B10: Units: | C10: S&P Capital IQ (Default) | E10: Decimals: | F10: Capital IQ (Default)
B11: Source: | C11: Capital IQ & Proprietary Data
A14: Income Statement
A15: For the Fiscal Period Ending | B15: 12 months Sep-28-2013 | C15: 12 months Sep-27-2014 | D15: 12 months Sep-26-2015 | E15: 12 months Sep-24-2016 | F15: 12 months Sep-30-2017 | G15: 12 months Sep-29-2018 | H15: 12 months Sep-28-2019 | I15: 12 months Sep-26-2020 | J15: 12 months Sep-25-2021 | K15: 12 months Sep-24-2022 | L15: 12 months Sep-30-2023 | M15: LTM 12 months Dec-30-2023
A16: Currency | B16: USD | C16: USD | D16: USD | E16: USD | F16: USD | G16: USD | H16: USD | I16: USD | J16: USD | K16: USD | L16: USD | M16: USD
A18: Revenue | B18: 170910 | C18: 182795 | D18: 233715 | E18: 215639 | F18: 229234 | G18: 265595 | H18: 260174 | I18: 274515 | J18: 365817 | K18: 394328 | L18: 383285 | M18: 385706
A19: = Net Sales | B19: 170910 | C19: 182795 | D19: 233715 | E19: 215639 | F19: - | G19: - | H19: - | I19: - | J19: - | K19: - | L19: - | M19: -
A20: + Net Sale service | B20: - | C20: - | D20: - | E20: - | F20: 32700 | G20: 39748 | H20: 46291 | I20: 53768 | J20: 68425 | K20: 78129 | L20: 85200 | M20: -
A21: + Net Sales Product | B21: - | C21: - | D21: - | E21: - | F21: 196534 | G21: 225847 | H21: 213883 | I21: 220747 | J21: 297392 | K21: 316199 | L21: 298085 | M21: -
A22: Other Revenue | B22: - | C22: - | D22: - | E22: - | F22: - | G22: - | H22: - | I22: - | J22: - | K22: - | L22: - | M22: -
A23: Total Revenue | B23: 170910 | C23: 182795 | D23: 233715 | E23: 215639 | F23: 229234 | G23: 265595 | H23: 260174 | I23: 274515 | J23: 365817 | K23: 394328 | L23: 383285 | M23: 385706
A25: Cost Of Goods Sold | B25: 106606 | C25: 112258 | D25: 140089 | E25: 131376 | F25: 141048 | G25: 163756 | H25: 161782 | I25: 169559 | J25: 212981 | K25: 223546 | L25: 214137 | M25: 212035
A26: = Services | B26: - | C26: - | D26: - | E26: - | F26: 14711 | G26: 15592 | H26: 16786 | I26: 18273 | J26: 20715 | K26: 22075 | L26: 24855 | M26: -
A27: + Cost of Sales-product | B27: - | C27: - | D27: - | E27: - | F27: 126337 | G27: 148164 | H27: 144996 | I27: 151286 | J27: 192266 | K27: 201471 | L27: 189282 | M27: -
A28: + Cost of Sales | B28: 106606 | C28: 112258 | D28: 140089 | E28: 131376 | F28: - | G28: - | H28: - | I28: - | J28: - | K28: - | L28: - | M28: -
A29: - SBC (Cost of Revenues) | B29: 350 | C29: 450 | D29: 575 | E29: 769 | F29: - | G29: - | H29: - | I29: - | J29: - | K29: - | L29: - | M29: -
A30: + SBC (Cost of Revenues) | B30: 350 | C30: 450 | D30: 575 | E30: 769 | F30: - | G30: - | H30: - | I30: - | J30: - | K30: - | L30: - | M30: -
A31: Gross Profit | B31: 64304 | C31: 70537 | D31: 93626 | E31: 84263 | F31: 88186 | G31: 101839 | H31: 98392 | I31: 104956 | J31: 152836 | K31: 170782 | L31: 169148 | M31: 173671
O32: 5-yr avg | P32: Our Estimate(Using near term)
A33: Gross Margin (Product) | F33: =(F21-F27)/F21 -> 0.35717484 | G33: =(G21-G27)/G21 -> 0.34396295 | H33: =(H21-H27)/H21 -> 0.32207796 | I33: =(I21-I27)/I21 -> 0.31466339 | J33: =(J21-J27)/J21 -> 0.35349303 | K33: =(K21-K27)/K21 -> 0.3628348 | L33: =(L21-L27)/L21 -> 0.36500663 | O33: =AVERAGE(H33:L33) -> 0.34361516 | P33: 0.36
A34: Gross Margin (Service) | F34: =(F20-F26)/F20 -> 0.55012232 | G34: =(G20-G26)/G20 -> 0.60772869 | H34: =(H20-H26)/H20 -> 0.63738092 | I34: =(I20-I26)/I20 -> 0.66015102 | J34: =(J20-J26)/J20 -> 0.69725977 | K34: =(K20-K26)/K20 -> 0.71745447 | L34: =(L20-L26)/L20 -> 0.70827465 | O34: =AVERAGE(H34:L34) -> 0.68410416 | P34: 0.71
A36: Selling General & Admin Exp. | B36: 10830 | C36: 11993 | D36: 14329 | E36: 14194 | F36: 15261 | G36: 16705 | H36: 18245 | I36: 19916 | J36: 21973 | K36: 25094 | L36: 24932 | M36: 25111
A37: = Advertising Expenses | B37: 1100 | C37: - | D37: - | E37: - | F37: - | G37: - | H37: - | I37: - | J37: - | K37: - | L37: - | M37: -
A38: + Selling, General and Administrative | B38: - | C38: - | D38: - | E38: - | F38: 15261 | G38: 16705 | H38: 18245 | I38: 19916 | J38: 21973 | K38: 25094 | L38: 24932 | M38: -
A39: + Selling, General and Administrative | B39: 10830 | C39: 11993 | D39: 14329 | E39: 14194 | F39: - | G39: - | H39: - | I39: - | J39: - | K39: - | L39: - | M39: -
A40: - SBC (SG&A Exp.) | B40: 986 | C40: 1197 | D40: 1475 | E40: 1552 | F40: - | G40: - | H40: - | I40: - | J40: - | K40: - | L40: - | M40: -
A41: - Advertising Expenses | B41: 1100 | C41: - | D41: - | E41: - | F41: - | G41: - | H41: - | I41: - | J41: - | K41: - | L41: - | M41: -
A42: + SBC (SG&A Exp.) | B42: 986 | C42: 1197 | D42: 1475 | E42: 1552 | F42: - | G42: - | H42: - | I42: - | J42: - | K42: - | L42: - | M42: -
A43: R & D Exp. | B43: 4475 | C43: 6041 | D43: 8067 | E43: 10045 | F43: 11581 | G43: 14236 | H43: 16217 | I43: 18752 | J43: 21914 | K43: 26251 | L43: 29915 | M43: 29902
A44: = Research and Development | B44: - | C44: - | D44: - | E44: - | F44: 11581 | G44: 14236 | H44: 16217 | I44: 18752 | J44: 21914 | K44: 26251 | L44: 29915 | M44: -
A45: + Research and Development | B45: 4475 | C45: 6041 | D45: 8067 | E45: 10045 | F45: - | G45: - | H45: - | I45: - | J45: - | K45: - | L45: - | M45: -
A46: - SBC (R&D Exp.) | B46: 917 | C46: 1216 | D46: 1536 | E46: 1889 | F46: - | G46: - | H46: - | I46: - | J46: - | K46: - | L46: - | M46: -
A47: + SBC (R&D Exp.) | B47: 917 | C47: 1216 | D47: 1536 | E47: 1889 | F47: - | G47: - | H47: - | I47: - | J47: - | K47: - | L47: - | M47: -
A48: Depreciation & Amort. | B48: - | C48: - | D48: - | E48: - | F48: - | G48: - | H48: - | I48: - | J48: - | K48: - | L48: - | M48: -
A49: Other Operating Expense/(Income) | B49: - | C49: - | D49: - | E49: - | F49: - | G49: - | H49: - | I49: - | J49: - | K49: - | L49: - | M49: -
A51: Other Operating Exp., Total | B51: 15305 | C51: 18034 | D51: 22396 | E51: 24239 | F51: 26842 | G51: 30941 | H51: 34462 | I51: 38668 | J51: 43887 | K51: 51345 | L51: 54847 | M51: 55013
O52: 5-yr avg | P52: Our Estimate
A53: Operating Expense/Revenue | B53: =B51/B23 -> 0.089550056 | C53: =C51/C23 -> 0.098656965 | D53: =D51/D23 -> 0.095826113 | E53: =E51/E23 -> 0.11240546 | F53: =F51/F23 -> 0.11709432 | G53: =G51/G23 -> 0.11649692 | H53: =H51/H23 -> 0.13245751 | I53: =I51/I23 -> 0.14085933 | ... L53: =L51/L23 -> 0.14309717 | O53: =AVERAGE(H53:L53) -> 0.13331854 | P53: =O53 -> 0.13331854
A55: Operating Income | B55: 48999 | C55: 52503 | D55: 71230 | E55: 60024 | F55: 61344 | G55: 70898 | H55: 63930 | I55: 66288 | J55: 108949 | K55: 119437 | L55: 114301 | M55: 118658
A57: Interest Expense | B57: -136 | C57: -384 | D57: -733 | E57: -1456 | F57: -2323 | G57: -3240 | H57: -3576 | I57: -2873 | J57: -2645 | K57: -2931 | L57: -3933 | M57: -3933
A58: = Interest Expense | B58: - | C58: -384 | D58: - | E58: -1456 | F58: -2323 | G58: -3240 | H58: -3576 | I58: -2873 | J58: -2645 | K58: -2931 | L58: -3933 | M58: -
A59: + Interest Expense | B59: -136 | C59: - | D59: - | E59: - | F59: - | G59: - | H59: - | I59: - | J59: - | K59: - | L59: - | M59: -
A60: + Interest Expense | B60: - | C60: - | D60: -733 | E60: - | F60: - | G60: - | H60: - | I60: - | J60: - | K60: - | L60: - | M60: -
A61: Interest and Invest. Income | B61: 1616 | C61: 1795 | D61: 2921 | E61: 3999 | F61: 5201 | G61: 5686 | H61: 4961 | I61: 3763 | J61: 2843 | K61: 2825 | L61: 3750 | M61: 3750
A62: = Interest and Investment Income | B62: 1616 | C62: 1795 | D62: - | E62: 3999 | F62: 5201 | G62: 5686 | H62: 4961 | I62: 3763 | J62: 2843 | K62: 2825 | L62: 3750 | M62: -
A63: + Interest and Investment Income | B63: - | C63: - | D63: 2921 | E63: - | F63: - | G63: - | H63: - | I63: - | J63: - | K63: - | L63: - | M63: -
A64: Net Interest Exp. | B64: 1480 | C64: 1411 | D64: 2188 | E64: 2543 | F64: 2878 | G64: 2446 | H64: 1385 | I64: 890 | J64: 198 | K64: -106 | L64: -183 | M64: -183
A66: Other Non-Operating Inc. (Exp.) | B66: -324 | C66: -431 | D66: -903 | E66: -1195 | F66: -133 | G66: -441 | H66: 422 | I66: -87 | J66: 60 | K66: -228 | L66: -382 | M66: -39
A67: = Other Income/expense-net | B67: - | C67: - | D67: - | E67: - | F67: - | G67: 2005 | H67: 1807 | I67: 803 | J67: 258 | K67: -334 | L67: -565 | M67: -
A68: - Interest and Investment Income | B68: - | C68: - | D68: - | E68: - | F68: - | G68: 5686 | H68: 4961 | I68: 3763 | J68: 2843 | K68: 2825 | L68: 3750 | M68: -
A69: - Interest Expense | B69: - | C69: - | D69: - | E69: - | F69: - | G69: -3240 | H69: -3576 | I69: -2873 | J69: -2645 | K69: -2931 | L69: -3933 | M69: -
A70: + Other Income/expense-net | B70: 1156 | C70: 980 | D70: 1285 | E70: 1348 | F70: 2745 | G70: - | H70: - | I70: - | J70: - | K70: - | L70: - | M70: -
A71: - Interest and Investment Income | B71: 1616 | C71: 1795 | D71: - | E71: 3999 | F71: 5201 | G71: - | H71: - | I71: - | J71: - | K71: - | L71: - | M71: -
A72: - Interest Expense | B72: - | C72: -384 | D72: - | E72: -1456 | F72: -2323 | G72: - | H72: - | I72: - | J72: - | K72: - | L72: - | M72: -
A73: - Interest and Investment Income | B73: -136 | C73: - | D73: 2921 | E73: - | F73: - | G73: - | H73: - | I73: - | J73: - | K73: - | L73: - | M73: -
A74: - Interest Expense | B74: - | C74: - | D74: -733 | E74: - | F74: - | G74: - | H74: - | I74: - | J74: - | K74: - | L74: - | M74: -
A75: EBT Excl. Unusual Items | B75: 50155 | C75: 53483 | D75: 72515 | E75: 61372 | F75: 64089 | G75: 72903 | H75: 65737 | I75: 67091 | J75: 109207 | K75: 119103 | L75: 113736 | M75: 118436
A77: Impairment of Goodwill | B77: - | C77: - | D77: - | E77: - | F77: - | G77: - | H77: - | I77: - | J77: - | K77: - | L77: - | M77: -
A78: Other Unusual Items | B78: - | C78: - | D78: - | E78: - | F78: - | G78: - | H78: - | I78: - | J78: - | K78: - | L78: - | M78: -
A79: EBT Incl. Unusual Items | B79: 50155 | C79: 53483 | D79: 72515 | E79: 61372 | F79: 64089 | G79: 72903 | H79: 65737 | I79: 67091 | J79: 109207 | K79: 119103 | L79: 113736 | M79: 118436
A81: Income Tax Expense | B81: 13118 | C81: 13973 | D81: 19121 | E81: 15685 | F81: 15738 | G81: 13372 | H81: 10481 | I81: 9680 | J81: 14527 | K81: 19300 | L81: 16741 | M81: 17523
A82: = Provision for Income Tax | B82: 13118 | C82: 13973 | D82: 19121 | E82: 15685 | F82: 15738 | G82: 13372 | H82: 10481 | I82: 9680 | J82: 14527 | K82: 19300 | L82: 16741 | M82: -
A83: Earnings from Cont. Ops. | B83: 37037 | C83: 39510 | D83: 53394 | E83: 45687 | F83: 48351 | G83: 59531 | H83: 55256 | I83: 57411 | J83: 94680 | K83: 99803 | L83: 96995 | M83: 100913 | O83: 5-yr avg by FY
A84: Tax Rate (Excl Unusual) | B84: =B81/B75 -> 0.2615492 | C84: =C81/C75 -> 0.26126059 | D84: =D81/D75 -> 0.26368338 | E84: =E81/E75 -> 0.25557257 | F84: =F81/F75 -> 0.24556476 | G84: =G81/G75 -> 0.18342181 | H84: =H81/H75 -> 0.15943837 | I84: =I81/I75 -> 0.14428165 | ... M84: =M81/M75 -> 0.14795333 | O84: =AVERAGE(H84:L84) -> 0.1491958
A85: Tax Rate (Incl Unusual) | B85: =B81/B79 -> 0.2615492 | C85: =C81/C79 -> 0.26126059 | D85: =D81/D79 -> 0.26368338 | E85: =E81/E79 -> 0.25557257 | F85: =F81/F79 -> 0.24556476 | G85: =G81/G79 -> 0.18342181 | H85: =H81/H79 -> 0.15943837 | I85: =I81/I79 -> 0.14428165 | ... M85: =M81/M79 -> 0.14795333 | O85: =AVERAGE(H85:L85) -> 0.1491958
A87: Earnings of Discontinued Ops. | B87: - | C87: - | D87: - | E87: - | F87: - | G87: - | H87: - | I87: - | J87: - | K87: - | L87: - | M87: -
A88: Extraord. Item & Account. Change | B88: - | C88: - | D88: - | E88: - | F88: - | G88: - | H88: - | I88: - | J88: - | K88: - | L88: - | M88: -
A89: Net Income to Company | B89: 37037 | C89: 39510 | D89: 53394 | E89: 45687 | F89: 48351 | G89: 59531 | H89: 55256 | I89: 57411 | J89: 94680 | K89: 99803 | L89: 96995 | M89: 100913
A91: Minority Int. in Earnings | B91: - | C91: - | D91: - | E91: - | F91: - | G91: - | H91: - | I91: - | J91: - | K91: - | L91: - | M91: -
A92: Net Income | B92: 37037 | C92: 39510 | D92: 53394 | E92: 45687 | F92: 48351 | G92: 59531 | H92: 55256 | I92: 57411 | J92: 94680 | K92: 99803 | L92: 96995 | M92: 100913
A94: Pref. Dividends and Other Adj. | B94: - | C94: - | D94: - | E94: - | F94: - | G94: - | H94: - | I94: - | J94: - | K94: - | L94: - | M94: -
A96: NI to Common Incl Extra Items | B96: 37037 | C96: 39510 | D96: 53394 | E96: 45687 | F96: 48351 | G96: 59531 | H96: 55256 | I96: 57411 | J96: 94680 | K96: 99803 | L96: 96995 | M96: 100913
A97: NI to Common Excl. Extra Items | B97: 37037 | C97: 39510 | D97: 53394 | E97: 45687 | F97: 48351 | G97: 59531 | H97: 55256 | I97: 57411 | J97: 94680 | K97: 99803 | L97: 96995 | M97: 100913
A99: Per Share Items
A100: Basic EPS | B100: 1.43 | C100: 1.62 | D100: 2.32 | E100: 2.09 | F100: 2.32 | G100: 3 | H100: 2.99 | I100: 3.31 | J100: 5.67 | K100: 6.15 | L100: 6.16 | M100: 6.45
A101: Basic EPS Excl. Extra Items | B101: 1.429487 | C101: 1.623101 | D101: 2.320097 | E101: 2.087758 | F101: 2.316885 | G101: 3.003353 | H101: 2.991445 | I101: 3.308587 | J101: 5.669029 | K101: 6.154614 | L101: 6.160669 | M101: 6.448736
A102: Weighted Avg. Basic Shares Out. | B102: 25909.28 | C102: 24342.288 | D102: 23013.684 | E102: 21883.28 | F102: 20868.968 | G102: 19821.51 | H102: 18471.336 | I102: 17352.119 | J102: 16701.272 | K102: 16215.963 | L102: 15744.231 | M102: 15648.491
A104: Diluted EPS | B104: 1.42 | C104: 1.61 | D104: 2.31 | E104: 2.08 | F104: 2.3 | G104: 2.98 | H104: 2.97 | I104: 3.28 | J104: 5.61 | K104: 6.11 | L104: 6.13 | M104: 6.42
A105: Diluted EPS Excl. Extra Items | B105: 1.42 | C105: 1.6125 | D105: 2.305 | E105: 2.0775 | F105: 2.3025 | G105: 2.98 | H105: 2.97 | I105: 3.28 | J105: 5.61 | K105: 6.11 | L105: 6.13 | M105: 6.418925 | O105: Diluted/Basic
A106: Weighted Avg. Diluted Shares Out. | B106: 26086.536 | C106: 24490.652 | D106: 23172.276 | E106: 22001.124 | F106: 21006.768 | G106: 20000.435 | H106: 18595.651 | I106: 17528.214 | J106: 16864.919 | K106: 16325.819 | L106: 15812.547 | M106: 15717.778 | O106: =M106/M102 -> 1.0044277
A108: Normalized Basic EPS | B108: 1.21 | C108: 1.37 | D108: 1.97 | E108: 1.75 | F108: 1.92 | G108: 2.3 | H108: 2.22 | I108: 2.42 | J108: 4.09 | K108: 4.59 | L108: 4.51 | M108: 4.73
A109: Normalized Diluted EPS | B109: 1.201649 | C109: 1.364883 | D109: 1.955866 | E109: 1.743433 | F109: 1.906796 | G109: 2.278169 | H109: 2.209421 | I109: 2.39225 | J109: 4.047121 | K109: 4.55961 | L109: 4.49548 | M109: 4.709476
A111: Dividends per Share | B111: 0.41 | C111: 0.46 | D111: 0.5 | E111: 0.55 | F111: 0.6 | G111: 0.68 | H111: 0.75 | I111: 0.8 | J111: 0.85 | K111: 0.9 | L111: 0.94 | M111: 0.95
A112: Payout Ratio % | B112: 0.285228 | C112: 0.281599 | D112: 0.216522 | E112: 0.265939 | F112: 0.264089 | G112: 0.230333 | H112: 0.255519 | I112: 0.245266 | J112: 0.152798 | K112: 0.148702 | L112: 0.154904 | M112: 0.149455
A114: Shares per Depository Receipt | B114: 0.1 | C114: 0.1 | D114: 0.1 | E114: 0.1 | F114: 0.1 | G114: 0.1 | H114: 0.1 | I114: 0.1 | J114: 0.1 | K114: 0.1 | L114: 0.1 | M114: 0.1
A116: Supplemental Items
A117: EBITDA | B117: 55756 | C117: 60449 | D117: 82487 | E117: 70529 | F117: 71501 | G117: 81801 | H117: 76477 | I117: 77344 | J117: 120233 | K117: 130541 | L117: 125820 | M117: 130109
A118: EBITA | B118: 49959 | C118: 53603 | D118: 72530 | E118: 60024 | F118: 61344 | G118: 70898 | H118: 63930 | I118: 66288 | J118: 108949 | K118: 119437 | L118: 114301 | M118: 118658
A119: EBIT | B119: 48999 | C119: 52503 | D119: 71230 | E119: 60024 | F119: 61344 | G119: 70898 | H119: 63930 | I119: 66288 | J119: 108949 | K119: 119437 | L119: 114301 | M119: 118658
A120: EBITDAR | B120: 56401 | C120: 61166 | D120: 83281 | E120: 71468 | F120: 72601 | G120: 83001 | H120: 77777 | I120: 88144 | J120: 134833 | K120: 147341 | L120: 141720 | M120: NA
A121: As Reported Total Revenue* | B121: NA | C121: NA | D121: NA | E121: NA | F121: 229234 | G121: 265595 | H121: 260174 | I121: 274515 | J121: 365817 | K121: 394328 | L121: 383285 | M121: 385706
A122: Effective Tax Rate % | B122: 0.261549 | C122: 0.26126 | D122: 0.263683 | E122: 0.255572 | F122: 0.245564 | G122: 0.183421 | H122: 0.159438 | I122: 0.144281 | J122: 0.133022 | K122: 0.162044 | L122: 0.147191 | M122: 0.147953
A123: Current Domestic Taxes | B123: 10418 | C123: 9479 | D123: 12995 | E123: 8642 | F123: 8101 | G123: 41976 | H123: 6859 | I123: 6761 | J123: 9877 | K123: 9409 | L123: 11015 | M123: 11015
A124: Current Foreign Taxes | B124: 1559 | C124: 2147 | D124: 4744 | E124: 2105 | F124: 1671 | G124: 3986 | H124: 3962 | I124: 3134 | J124: 9424 | K124: 8996 | L124: 8750 | M124: 8750
A125: Total Current Taxes | B125: 11977 | C125: 11626 | D125: 17739 | E125: 10747 | F125: 9772 | G125: 45962 | H125: 10821 | I125: 9895 | J125: 19301 | K125: 18405 | L125: 19765 | M125: 19765
A126: Deferred Domestic Taxes | B126: 1567 | C126: 3005 | D126: 3188 | E126: 4905 | F126: 5982 | G126: -33771 | H126: -3006 | I126: -3598 | J126: -7514 | K126: -2181 | L126: -3693 | M126: -3693
...

Sheet BS
A5: Apple Inc. (NasdaqGS:AAPL) > Financials > Balance Sheet
A7: In Millions of the reported currency, except per share items. | B7: Template: | C7: Standard | E7: Restatement: | F7: Latest Filings
B8: Period Type: | C8: Annual | E8: Order: | F8: Latest on Right
B9: Currency: | C9: Reported Currency | E9: Conversion: | F9: Historical
B10: Units: | C10: S&P Capital IQ (Default) | E10: Decimals: | F10: Capital IQ (Default)
B11: Source: | C11: Capital IQ & Proprietary Data
A14: Balance Sheet
A15: Balance Sheet as of: | B15: 41545 | C15: 41909 | D15: Restated Sep-26-2015 | E15: 42637 | F15: 43008 | G15: Reclassified Sep-29-2018 | H15: 43736 | I15: 44100 | J15: 44464 | K15: 44828 | L15: 45199 | M15: 45290
A16: Currency | B16: USD | C16: USD | D16: USD | E16: USD | F16: USD | G16: USD | H16: USD | I16: USD | J16: USD | K16: USD | L16: USD | M16: USD
A17: ASSETS | P17: Net Debt Calculation | Q17: FY24Q1
A18: Cash And Equivalents | B18: 14259 | C18: 13844 | D18: 21120 | E18: 20484 | F18: 20289 | G18: 25913 | H18: 48844 | I18: 38016 | J18: 34940 | K18: 23646 | L18: 29965 | M18: 40760 | P18: Debt | Q18: =M111+M116+M137+M141 -> 106042
A19: = Cash and Cash Equivalents | B19: 14259 | C19: 13844 | D19: 21120 | E19: 20484 | F19: 20289 | G19: 25913 | H19: 48844 | I19: 38016 | J19: 34940 | K19: 23646 | L19: 29965 | M19: - | P19: Cash | Q19: =M26 -> 73100
A20: + Cash and Cash Equivalents | B20: - | C20: - | D20: - | E20: - | F20: - | G20: - | H20: - | I20: - | J20: - | K20: - | L20: - | M20: 40760 | P20: Net Debt | Q20: =Q18-Q19 -> 32942
A21: Short Term Investments | B21: 26287 | C21: 11233 | D21: 20481 | E21: 46671 | F21: 53892 | G21: 40388 | H21: 51713 | I21: 52927 | J21: 27699 | K21: 24658 | L21: 31590 | M21: 32340
A22: = Short-term Investments | B22: - | C22: - | D22: - | E22: - | F22: - | G22: - | H22: - | I22: - | J22: - | K22: - | L22: - | M22: 32340
A23: + Short-term Marketable Securities | B23: 26287 | C23: 11233 | D23: 20481 | E23: 46671 | F23: 53892 | G23: 40388 | H23: 51713 | I23: 52927 | J23: 27699 | K23: 24658 | L23: 31590 | M23: -
A24: Trading Asset Securities | B24: 44 | C24: 81 | D24: 394 | E24: - | F24: - | G24: - | H24: - | I24: - | J24: - | K24: - | L24: - | M24: -
A25: = Derivative Trading Asset Securities | B25: 44 | C25: 81 | D25: 394 | E25: - | F25: - | G25: - | H25: - | I25: - | J25: - | K25: - | L25: - | M25: -
A26: Total Cash & ST Investments | B26: 40590 | C26: 25158 | D26: 41995 | E26: 67155 | F26: 74181 | G26: 66301 | H26: 100557 | I26: 90943 | J26: 62639 | K26: 48304 | L26: 61555 | M26: 73100
A28: Accounts Receivable | B28: 13102 | C28: 17460 | D28: 16849 | E28: 15754 | F28: 17874 | G28: 23186 | H28: 22926 | I28: 16120 | J28: 26278 | K28: 28184 | L28: 29508 | M28: 23194
A29: = Accounts Receivables | B29: - | C29: - | D29: - | E29: - | F29: 17874 | G29: 23186 | H29: 22926 | I29: 16120 | J29: 26278 | K29: 28184 | L29: 29508 | M29: -
A30: + Allowance for Doubtful Accounts Receivable | B30: -99 | C30: -86 | D30: -63 | E30: -53 | F30: - | G30: - | H30: - | I30: - | J30: - | K30: - | L30: - | M30: -
A31: + Accounts Receivables | B31: 13102 | C31: 17460 | D31: 16849 | E31: 15754 | F31: - | G31: - | H31: - | I31: - | J31: - | K31: - | L31: - | M31: 23194
A32: - Allowance for Doubtful Accounts Receivable | B32: -99 | C32: -86 | D32: -63 | E32: -53 | F32: - | G32: - | H32: - | I32: - | J32: - | K32: - | L32: - | M32: -
A33: Other Receivables | B33: 7539 | C33: 9759 | D33: 13494 | E33: 13545 | F33: 17799 | G33: 25809 | H33: 22878 | I33: 21325 | J33: 25228 | K33: 32748 | L33: 31477 | M33: 26908
A34: = Other Receivables | B34: - | C34: - | D34: - | E34: - | F34: - | G34: - | H34: - | I34: - | J34: - | K34: - | L34: - | M34: 26908
A35: + Vendor non-trade receivables | B35: 7539 | C35: 9759 | D35: 13494 | E35: 13545 | F35: 17799 | G35: 25809 | H35: 22878 | I35: 21325 | J35: 25228 | K35: 32748 | L35: 31477 | M35: -
A36: Total Receivables | B36: 20641 | C36: 27219 | D36: 30343 | E36: 29299 | F36: 35673 | G36: 48995 | H36: 45804 | I36: 37445 | J36: 51506 | K36: 60932 | L36: 60985 | M36: 50102
A38: Inventory | B38: 1764 | C38: 2111 | D38: 2349 | E38: 2132 | F38: 4855 | G38: 3956 | H38: 4106 | I38: 4061 | J38: 6580 | K38: 4946 | L38: 6331 | M38: 6511
A39: = Inventories | B39: - | C39: 2111 | D39: 2349 | E39: 2132 | F39: 4855 | G39: 3956 | H39: 4106 | I39: 4061 | J39: 6580 | K39: 4946 | L39: 6331 | M39: -
A40: + Inventory | B40: - | C40: - | D40: - | E40: - | F40: - | G40: - | H40: - | I40: - | J40: - | K40: - | L40: - | M40: 6511
A41: + Inventories - Raw Materials | B41: 683 | C41: - | D41: - | E41: - | F41: - | G41: - | H41: - | I41: - | J41: - | K41: - | L41: - | M41: -
A42: + Inventories - Finished Goods | B42: 1081 | C42: - | D42: - | E42: - | F42: - | G42: - | H42: - | I42: - | J42: - | K42: - | L42: - | M42: -
A43: Deferred Tax Assets, Curr. | B43: 3453 | C43: 4318 | D43: - | E43: - | F43: - | G43: - | H43: - | I43: - | J43: - | K43: - | L43: - | M43: -
A44: = Deferred Tax Assets | B44: 3453 | C44: 4318 | D44: - | E44: - | F44: - | G44: - | H44: - | I44: - | J44: - | K44: - | L44: - | M44: -
A45: Restricted Cash | B45: - | C45: - | D45: - | E45: - | F45: - | G45: - | H45: 23 | I45: - | J45: - | K45: - | L45: - | M45: -
A46: = Restricted Cash | B46: - | C46: - | D46: - | E46: - | F46: - | G46: - | H46: 23 | I46: - | J46: - | K46: - | L46: - | M46: -
A47: Other Current Assets | B47: 6838 | C47: 9725 | D47: 14691 | E47: 8283 | F47: 13936 | G47: 12087 | H47: 12329 | I47: 11264 | J47: 14111 | K47: 21223 | L47: 14695 | M47: 13979
A48: = Other Current Assets | B48: - | C48: - | D48: - | E48: 8283 | F48: 13936 | G48: 12087 | H48: - | I48: 11264 | J48: 14111 | K48: 21223 | L48: 14695 | M48: -
A49: + Other Current Assets | B49: 6882 | C49: 9806 | D49: 15085 | E49: - | F49: - | G49: - | H49: 12352 | I49: - | J49: - | K49: - | L49: - | M49: 13979
A50: - Derivative Assets, Current | B50: 170 | C50: 1554 | D50: 1551 | E50: - | F50: - | G50: - | H50: 23 | I50: - | J50: - | K50: - | L50: - | M50: -
A51: - Derivative Trading Asset Securities | B51: 44 | C51: 81 | D51: 394 | E51: - | F51: - | G51: - | H51: - | I51: - | J51: - | K51: - | L51: - | M51: -
A52: + Derivative Assets, Current | B52: 170 | C52: 1554 | D52: 1551 | E52: - | F52: - | G52: - | H52: - | I52: - | J52: - | K52: - | L52: - | M52: -
A53: Total Current Assets | B53: 73286 | C53: 68531 | D53: 89378 | E53: 106869 | F53: 128645 | G53: 131339 | H53: 162819 | I53: 143713 | J53: 134836 | K53: 135405 | L53: 143566 | M53: 143692
A55: Gross Property, Plant & Equipment | B55: 28519 | C55: 39015 | D55: 49257 | E55: 61245 | F55: 75076 | G55: 90403 | H55: 95957 | I55: 112096 | J55: 119810 | K55: 124874 | L55: 125260 | M55: 116176
A56: = Right-of-Use asset-Operating lease-Gross | B56: - | C56: - | D56: - | E56: - | F56: - | G56: - | H56: - | I56: 8570 | J56: 10087 | K56: 10417 | L56: 10661 | M56: -
A57: + Land | B57: 3309 | C57: 4863 | D57: - | E57: 10185 | F57: 13587 | G57: 16216 | H57: 17085 | I57: 17952 | J57: 20041 | K57: 22126 | L57: 23446 | M57: -
A58: + Land | B58: - | C58: - | D58: 6956 | E58: - | F58: - | G58: - | H58: - | I58: - | J58: - | K58: - | L58: - | M58: -
A59: + Leasehold Improvements | B59: 3968 | C59: 4513 | D59: - | E59: 6517 | F59: 7279 | G59: 8205 | H59: 9075 | I59: 10283 | J59: 11023 | K59: 11271 | L59: 12839 | M59: -
A60: + Leasehold Improvements | B60: - | C60: - | D60: 5263 | E60: - | F60: - | G60: - | H60: - | I60: - | J60: - | K60: - | L60: - | M60: -
A61: + Machinery | B61: 21242 | C61: 29639 | D61: - | E61: 44543 | F61: 54210 | G61: 65982 | H61: 69797 | I61: 75291 | J61: 78659 | K61: 81060 | L61: 78314 | M61: -
A62: + Machinery | B62: - | C62: - | D62: 37038 | E62: - | F62: - | G62: - | H62: - | I62: - | J62: - | K62: - | L62: - | M62: -
A63: + Gross Property Plant and Equipment | B63: - | C63: - | D63: - | E63: - | F63: - | G63: - | H63: - | I63: - | J63: - | K63: - | L63: - | M63: 116176
A64: Accumulated Depreciation | B64: -11922 | C64: -18391 | D64: -26786 | E64: -34235 | F64: -41293 | G64: -49099 | H64: -58579 | I64: -66760 | J64: -70283 | K64: -72340 | L64: -70884 | M64: -72510
A65: = Accumulated Depreciation | B65: - | C65: - | D65: -26786 | E65: - | F65: - | G65: - | H65: - | I65: - | J65: - | K65: - | L65: - | M65: -72510
A66: + Accumulated Depreciation | B66: -11922 | C66: -18391 | D66: - | E66: -34235 | F66: -41293 | G66: -49099 | H66: -58579 | I66: -66760 | J66: -70283 | K66: -72340 | L66: -70884 | M66: -
A67: Net Property, Plant & Equipment | B67: 16597 | C67: 20624 | D67: 22471 | E67: 27010 | F67: 33783 | G67: 41304 | H67: 37378 | I67: 45336 | J67: 49527 | K67: 52534 | L67: 54376 | M67: 43666
A69: Long-term Investments | B69: 106215 | C69: 130162 | D69: 164065 | E69: 170430 | F69: 194714 | G69: 170799 | H69: 105341 | I69: 100887 | J69: 127877 | K69: 120805 | L69: 100544 | M69: 99475
A70: = Long Term Marketable Securities | B70: - | C70: - | D70: - | E70: - | F70: - | G70: - | H70: - | I70: - | J70: - | K70: - | L70: - | M70: 99475
A71: + Long-term Marketable Securities | B71: 106215 | C71: 130162 | D71: 164065 | E71: 170430 | F71: 194714 | G71: 170799 | H71: 105341 | I71: 100887 | J71: 127877 | K71: 120805 | L71: 100544 | M71: -
A72: Goodwill | B72: 1577 | C72: 4616 | D72: 5116 | E72: 5414 | F72: - | G72: - | H72: - | I72: - | J72: - | K72: - | L72: - | M72: -
A73: = Goodwill | B73: 1577 | C73: 4616 | D73: 5116 | E73: 5414 | F73: - | G73: - | H73: - | I73: - | J73: - | K73: - | L73: - | M73: -
A74: Other Intangibles | B74: 4179 | C74: 4142 | D74: 3893 | E74: 3206 | F74: - | G74: - | H74: - | I74: - | J74: - | K74: - | L74: - | M74: -
A75: = Accumulated Amortization of Intangible Assets | B75: -2002 | C75: -3085 | D75: -4332 | E75: -5806 | F75: - | G75: - | H75: - | I75: - | J75: - | K75: - | L75: - | M75: -
A76: + Gross Intangible Assets | B76: 6181 | C76: 7127 | D76: 8225 | E76: 9012 | F76: - | G76: - | H76: - | I76: - | J76: - | K76: - | L76: - | M76: -
A77: + Gross Intangible Assets | B77: - | C77: 100 | D77: - | E77: - | F77: - | G77: - | H77: - | I77: - | J77: - | K77: - | L77: - | M77: -
A78: Other Long-Term Assets | B78: 5146 | C78: 3764 | D78: 5422 | E78: 8757 | F78: 18177 | G78: 22283 | H78: 32978 | I78: 33952 | J78: 38762 | K78: 44011 | L78: 54097 | M78: 66681
A79: = Other Assets | B79: 5146 | C79: 3764 | D79: 5422 | E79: 8757 | F79: 18177 | G79: 22283 | H79: - | I79: - | J79: - | K79: - | L79: - | M79: -
A80: + Other Assets | B80: - | C80: - | D80: - | E80: - | F80: - | G80: - | H80: 32978 | I80: 42522 | J80: 48849 | K80: 54428 | L80: 64758 | M80: 66681
A81: - Cash Restricted, Long-Term | B81: - | C81: - | D81: - | E81: - | F81: - | G81: - | H81: 1357 | I81: 8570 | J81: 10087 | K81: 10417 | L81: 10661 | M81: -
A82: + Cash Restricted, Long-Term | B82: - | C82: - | D82: - | E82: - | F82: - | G82: - | H82: 1357 | I82: - | J82: - | K82: - | L82: - | M82: -
A83: Total Assets | B83: 207000 | C83: 231839 | D83: 290345 | E83: 321686 | F83: 375319 | G83: 365725 | H83: 338516 | I83: 323888 | J83: 351002 | K83: 352755 | L83: 352583 | M83: 353514
A85: LIABILITIES
A86: Accounts Payable | B86: 22367 | C86: 30196 | D86: 35490 | E86: 37294 | F86: 44242 | G86: 55888 | H86: 46236 | I86: 42296 | J86: 54763 | K86: 64115 | L86: 62611 | M86: 58146
A87: = Accounts Payable | B87: 22367 | C87: 30196 | D87: 35490 | E87: 37294 | F87: 44242 | G87: 55888 | H87: 46236 | I87: 42296 | J87: 54763 | K87: 64115 | L87: 62611 | M87: -
A88: + Accounts Payable | B88: - | C88: - | D88: - | E88: - | F88: - | G88: - | H88: - | I88: - | J88: - | K88: - | L88: - | M88: 58146
A89: Accrued Exp. | B89: 8427 | C89: 18372 | D89: 23169 | E89: 21864 | F89: - | G89: - | H89: - | I89: - | J89: - | K89: - | L89: - | M89: -
A90: = Accrued Expenses | B90: 13856 | C90: 18453 | D90: 25181 | E90: 22027 | F90: - | G90: - | H90: - | I90: - | J90: - | K90: - | L90: - | M90: -
A91: - Other Current Liabilities | B91: 2967 | C91: 81 | D91: 999 | E91: 163 | F91: - | G91: - | H91: - | I91: - | J91: - | K91: - | L91: - | M91: -
A92: - Accrued Expenses | B92: 1291 | C92: - | D92: 13 | E92: - | F92: - | G92: - | H92: - | I92: - | J92: - | K92: - | L92: - | M92: -
A93: - Current Income Tax Payable | B93: 1200 | C93: - | D93: - | E93: - | F93: - | G93: - | H93: - | I93: - | J93: - | K93: - | L93: - | M93: -
A94: - Accrued Expenses | B94: 959 | C94: - | D94: 1000 | E94: - | F94: - | G94: - | H94: - | I94: - | J94: - | K94: - | L94: - | M94: -
A95: - Unearned Revenue, Current | B95: 1262 | C95: - | D95: - | E95: - | F95: - | G95: - | H95: - | I95: - | J95: - | K95: - | L95: - | M95: -
A96: - Accrued Expenses | B96: 6177 | C96: - | D96: - | E96: - | F96: - | G96: - | H96: - | I96: - | J96: - | K96: - | L96: - | M96: -
A97: + Accrued Expenses | B97: 13856 | C97: - | D97: - | E97: - | F97: - | G97: - | H97: - | I97: - | J97: - | K97: - | L97: - | M97: -
A98: - Warranty Liabilities | B98: 2967 | C98: - | D98: - | E98: - | F98: - | G98: - | H98: - | I98: - | J98: - | K98: - | L98: - | M98: -
A99: - Accrued Expenses | B99: 1291 | C99: - | D99: - | E99: - | F99: - | G99: - | H99: - | I99: - | J99: - | K99: - | L99: - | M99: -
A100: - Current Income Tax Payable | B100: 1200 | C100: - | D100: - | E100: - | F100: - | G100: - | H100: - | I100: - | J100: - | K100: - | L100: - | M100: -
A101: - Accrued Expenses | B101: 959 | C101: - | D101: - | E101: - | F101: - | G101: - | H101: - | I101: - | J101: - | K101: - | L101: - | M101: -
A102: - Unearned Revenue, Current | B102: 1262 | C102: - | D102: - | E102: - | F102: - | G102: - | H102: - | I102: - | J102: - | K102: - | L102: - | M102: -
A103: - Accrued Expenses | B103: 6177 | C103: - | D103: - | E103: - | F103: - | G103: - | H103: - | I103: - | J103: - | K103: - | L103: - | M103: -
A104: + Accrued Expenses | B104: 13856 | C104: - | D104: - | E104: - | F104: - | G104: - | H104: - | I104: - | J104: - | K104: - | L104: - | M104: -
A105: - Warranty Liabilities | B105: 2967 | C105: - | D105: - | E105: - | F105: - | G105: - | H105: - | I105: - | J105: - | K105: - | L105: - | M105: -
A106: - Current Income Tax Payable | B106: 1200 | C106: - | D106: - | E106: - | F106: - | G106: - | H106: - | I106: - | J106: - | K106: - | L106: - | M106: -
A107: - Unearned Revenue, Current | B107: 1262 | C107: - | D107: - | E107: - | F107: - | G107: - | H107: - | I107: - | J107: - | K107: - | L107: - | M107: -
A108: Short-term Borrowings | B108: - | C108: 6308 | D108: 8499 | E108: 8105 | F108: 11977 | G108: 11964 | H108: 5980 | I108: 4996 | J108: 6000 | K108: 9982 | L108: 5985 | M108: 1998
A109: = Loans Payable Current | B109: - | C109: - | D109: - | E109: - | F109: - | G109: - | H109: - | I109: - | J109: - | K109: - | L109: - | M109: 1998
A110: + Commercial Paper | B110: - | C110: 6308 | D110: 8499 | E110: 8105 | F110: 11977 | G110: 11964 | H110: 5980 | I110: 4996 | J110: 6000 | K110: 9982 | L110: 5985 | M110: -
A111: Curr. Port. of LT Debt | B111: - | C111: 0 | D111: 2513 | E111: 3500 | F111: 6496 | G111: 8784 | H111: 10260 | I111: 8773 | J111: 9613 | K111: 11128 | L111: 9822 | M111: 10954
A112: = Current Portion of Long-term Debt | B112: - | C112: - | D112: 2500 | E112: 3500 | F112: - | G112: - | H112: - | I112: - | J112: - | K112: - | L112: - | M112: -
...

Sheet CF
A5: Apple Inc. (NasdaqGS:AAPL) > Financials > Cash Flow
A7: In Millions of the reported currency, except per share items. | B7: Template: | C7: Standard | E7: Restatement: | F7: Latest Filings
B8: Period Type: | C8: Annual | E8: Order: | F8: Latest on Right
B9: Currency: | C9: Reported Currency | E9: Conversion: | F9: Historical
B10: Units: | C10: S&P Capital IQ (Default) | E10: Decimals: | F10: Capital IQ (Default)
B11: Source: | C11: Capital IQ & Proprietary Data
A14: Cash Flow
A15: For the Fiscal Period Ending | B15: 12 months Sep-28-2013 | C15: 12 months Sep-27-2014 | D15: 12 months Sep-26-2015 | E15: Restated 12 months Sep-24-2016 | F15: Restated 12 months Sep-30-2017 | G15: 12 months Sep-29-2018 | H15: 12 months Sep-28-2019 | I15: 12 months Sep-26-2020 | J15: 12 months Sep-25-2021 | K15: 12 months Sep-24-2022 | L15: 12 months Sep-30-2023 | M15: LTM 12 months Dec-30-2023
A16: Currency | B16: USD | C16: USD | D16: USD | E16: USD | F16: USD | G16: USD | H16: USD | I16: USD | J16: USD | K16: USD | L16: USD | M16: USD
A18: Net Income | B18: 37037 | C18: 39510 | D18: 53394 | E18: 45687 | F18: 48351 | G18: 59531 | H18: 55256 | I18: 57411 | J18: 94680 | K18: 99803 | L18: 96995 | M18: 100913
A19: Depreciation & Amort. | B19: 5797 | C19: 6846 | D19: 9957 | E19: 10505 | F19: 10157 | G19: 10903 | H19: 12547 | I19: 11056 | J19: 11284 | K19: 11104 | L19: 11519 | M19: 11451
A20: = Depreciation from Notes | B20: 5800 | C20: 6900 | D20: 9200 | E20: 8300 | F20: 8200 | G20: 9300 | H20: 11300 | I20: 9700 | J20: 9500 | K20: 8700 | L20: 8500 | M20: -
A21: + Depreciation and Amortization | B21: 6757 | C21: 7946 | D21: 11257 | E21: 10505 | F21: 10157 | G21: 10903 | H21: 12547 | I21: 11056 | J21: 11284 | K21: 11104 | L21: 11519 | M21: -
A22: - Depreciation from Notes | B22: 5800 | C22: 6900 | D22: 9200 | E22: 8300 | F22: 8200 | G22: 9300 | H22: 11300 | I22: 9700 | J22: 9500 | K22: 8700 | L22: 8500 | M22: -
A23: - Amortization of Intangible Assets | B23: 960 | C23: 1100 | D23: 1300 | E23: - | F23: - | G23: - | H23: - | I23: - | J23: - | K23: - | L23: - | M23: -
A24: Amort. of Goodwill and Intangibles | B24: 960 | C24: 1100 | D24: 1300 | E24: - | F24: - | G24: - | H24: - | I24: - | J24: - | K24: - | L24: - | M24: -
A25: = Amortization of Intangible Assets | B25: 960 | C25: 1100 | D25: 1300 | E25: - | F25: - | G25: - | H25: - | I25: - | J25: - | K25: - | L25: - | M25: -
A26: Depreciation & Amort., Total | B26: 6757 | C26: 7946 | D26: 11257 | E26: 10505 | F26: 10157 | G26: 10903 | H26: 12547 | I26: 11056 | J26: 11284 | K26: 11104 | L26: 11519 | M26: 11451
A28: Stock-Based Compensation | B28: 2253 | C28: 2863 | D28: 3586 | E28: 4210 | F28: 4840 | G28: 5340 | H28: 6068 | I28: 6829 | J28: 7906 | K28: 9038 | L28: 10833 | M28: 10925
A29: = Stock Based Compenation Expense | B29: 2253 | C29: 2863 | D29: 3586 | E29: 4210 | F29: 4840 | G29: 5340 | H29: 6068 | I29: 6829 | J29: 7906 | K29: 9038 | L29: 10833 | M29: -
A30: Other Operating Activities | B30: 1141 | C30: 2347 | D30: 1767 | E30: 5424 | F30: 5800 | G30: -33034 | H30: -992 | I30: -312 | J30: -4921 | K30: 1006 | L30: -2227 | M30: -2899
A31: = Others | B31: - | C31: - | D31: 385 | E31: 486 | F31: - | G31: -444 | H31: -652 | I31: -97 | J31: -4921 | K31: 1006 | L31: -2227 | M31: -
A32: + Deferred Income Tax Income/expense | B32: 1141 | C32: 2347 | D32: 1382 | E32: 4938 | F32: 5966 | G32: -32590 | H32: -340 | I32: -215 | J32: - | K32: - | L32: - | M32: -
A33: + Adjustments to Reconcile Net Income to Cash Generated By Operating Activities : Other | B33: - | C33: - | D33: - | E33: - | F33: -166 | G33: - | H33: - | I33: - | J33: - | K33: - | L33: - | M33: -
A34: Change in Acc. Receivable | B34: -2172 | C34: -4232 | D34: 417 | E34: 527 | F34: -2093 | G34: -5322 | H34: 245 | I34: 6917 | J34: -10125 | K34: -1823 | L34: -1688 | M34: 592
A35: = Accounts Receivable | B35: -2172 | C35: -4232 | D35: 417 | E35: 527 | F35: -2093 | G35: -5322 | H35: 245 | I35: 6917 | J35: -10125 | K35: -1823 | L35: -1688 | M35: -
A36: Change In Inventories | B36: -973 | C36: -76 | D36: -238 | E36: 217 | F36: -2723 | G36: 828 | H36: -289 | I36: -127 | J36: -2642 | K36: 1484 | L36: -1618 | M36: 52
A37: = Inventories | B37: -973 | C37: -76 | D37: -238 | E37: 217 | F37: -2723 | G37: 828 | H37: -289 | I37: -127 | J37: -2642 | K37: 1484 | L37: -1618 | M37: -
A38: Change in Acc. Payable | B38: 2340 | C38: 5938 | D38: 5001 | E38: 2117 | F38: 8966 | G38: 9175 | H38: -1923 | I38: -4062 | J38: 12326 | K38: 9448 | L38: -1889 | M38: -356
A39: = Accounts Payable | B39: 2340 | C39: 5938 | D39: 5001 | E39: 2117 | F39: 8966 | G39: 9175 | H39: -1923 | I39: -4062 | J39: 12326 | K39: 9448 | L39: -1889 | M39: -
A40: Change in Unearned Rev. | B40: 1459 | C40: 1460 | D40: 1042 | E40: -1554 | F40: -593 | G40: -3 | H40: -625 | I40: 2081 | J40: - | K40: - | L40: - | M40: -
A41: = Deferred Revenue | B41: 1459 | C41: 1460 | D41: 1042 | E41: -1554 | F41: -593 | G41: -3 | H41: -625 | I41: 2081 | J41: - | K41: - | L41: - | M41: -
A42: Change in Other Net Operating Assets | B42: 5824 | C42: 3957 | D42: 5040 | E42: -902 | F42: -8480 | G42: 30016 | H42: -896 | I42: 881 | J42: -4470 | K42: -7909 | L42: -1382 | M42: -4245
A43: = Other Current and Non-current Assets | B43: 1080 | C43: 167 | D43: -283 | E43: 1055 | F43: -5318 | G43: -423 | H43: 873 | I43: -9588 | J43: -8042 | K43: -6499 | L43: -5684 | M43: -
A44: + Other Current and Non-current Liabilities | B44: 4521 | C44: 6010 | D44: 9058 | E44: -1906 | F44: 1092 | G44: 38449 | H44: -4700 | I44: 8916 | J44: 7475 | K44: 6110 | L44: 3031 | M44: -
A45: + Vendor Non-trade Receivables | B45: 223 | C45: -2220 | D45: -3735 | E45: -51 | F45: -4254 | G45: -8010 | H45: 2931 | I45: 1553 | J45: -3903 | K45: -7520 | L45: 1271 | M45: -
A46: Cash from Ops. | B46: 53666 | C46: 59713 | D46: 81266 | E46: 66231 | F46: 64225 | G46: 77434 | H46: 69391 | I46: 80674 | J46: 104038 | K46: 122151 | L46: 110543 | M46: 116433
A48: Capital Expenditure | B48: -8165 | C48: -9571 | D48: -11247 | E48: -12734 | F48: -12451 | G48: -13313 | H48: -10495 | I48: -7309 | J48: -11085 | K48: -10708 | L48: -10959 | M48: -9564
A49: = Purchase of Property Plant, and Equipment | B49: -8165 | C49: -9571 | D49: -11247 | E49: -12734 | F49: -12451 | G49: -13313 | H49: -10495 | I49: -7309 | J49: -11085 | K49: -10708 | L49: -10959 | M49: -
A50: Cash Acquisitions | B50: -496 | C50: -3765 | D50: -343 | E50: -297 | F50: -329 | G50: -721 | H50: -624 | I50: -1524 | J50: - | K50: - | L50: - | M50: -
A51: = Payments Made in Connection With Business Acquisitions, Net of Cash Acquired | B51: -496 | C51: -3765 | D51: -343 | E51: -297 | F51: -329 | G51: -721 | H51: -624 | I51: -1524 | J51: - | K51: - | L51: - | M51: -
A52: Divestitures | B52: - | C52: - | D52: - | E52: - | F52: - | G52: - | H52: - | I52: - | J52: - | K52: - | L52: - | M52: -
A53: Sale (Purchase) of Intangible assets | B53: -911 | C53: -242 | D53: -241 | E53: - | F53: - | G53: - | H53: - | I53: - | J53: - | K53: - | L53: - | M53: -
A54: = Payment for Acquisition of Intangible Assets | B54: -911 | C54: -242 | D54: -241 | E54: - | F54: - | G54: - | H54: - | I54: - | J54: - | K54: - | L54: - | M54: -
A55: Invest. in Marketable & Equity Securt. | B55: -24042 | C55: -9027 | D55: -44417 | E55: -32022 | F55: -33542 | G55: 30845 | H55: 58093 | I55: 5453 | J55: -3075 | K55: -9560 | L55: 16001 | M55: 18121
A56: = Proceeds from Sale of Marketable Securities | B56: 104130 | C56: 189301 | D56: 107447 | E56: 90536 | F56: 94564 | G56: 47838 | H56: 56988 | I56: 50473 | J56: 47460 | K56: 37446 | L56: 5828 | M56: -
A57: + Purchases of Non-marketable Securities | B57: - | C57: - | D57: - | E57: -1388 | F57: -521 | G57: -1871 | H57: -1001 | I57: - | J57: - | K57: - | L57: - | M57: -
A58: + Purchase of Marketable Securities | B58: -148489 | C58: -217128 | D58: -166402 | E58: -142428 | F58: -159486 | G58: -71356 | H58: -39630 | I58: -114938 | J58: -109558 | K58: -76923 | L58: -29513 | M58: -
A59: + Proceeds from maturities of marketable securities | B59: 20317 | C59: 18810 | D59: 14538 | E59: 21258 | F59: 31775 | G59: 55881 | H59: 40102 | I59: 69918 | J59: 59023 | K59: 29917 | L59: 39686 | M59: -
A60: + Proceeds from Nonmarketable Securities | B60: - | C60: - | D60: - | E60: - | F60: 126 | G60: 353 | H60: 1634 | I60: - | J60: - | K60: - | L60: - | M60: -
A61: + Payments for Strategic Investments | B61: - | C61: -10 | D61: - | E61: - | F61: - | G61: - | H61: - | I61: - | J61: - | K61: - | L61: - | M61: -
A62: Net (Inc.) Dec. in Loans Originated/Sold | B62: - | C62: - | D62: - | E62: - | F62: - | G62: - | H62: - | I62: - | J62: - | K62: - | L62: - | M62: -
A63: Other Investing Activities | B63: -160 | C63: 26 | D63: -26 | E63: -924 | F63: -124 | G63: -745 | H63: -1078 | I63: -909 | J63: -385 | K63: -2086 | L63: -1337 | M63: -1480
A64: = Others | B64: -160 | C64: 26 | D64: -26 | E64: -924 | F64: -124 | G64: -745 | H64: -1078 | I64: -909 | J64: -385 | K64: -2086 | L64: -1337 | M64: -
A65: Cash from Investing | B65: -33774 | C65: -22579 | D65: -56274 | E65: -45977 | F65: -46446 | G65: 16066 | H65: 45896 | I65: -4289 | J65: -14545 | K65: -22354 | L65: 3705 | M65: 7077
A67: Short Term Debt Issued | B67: - | C67: 6306 | D67: 2191 | E67: - | F67: 3852 | G67: - | H67: - | I67: - | J67: 1022 | K67: 3955 | L67: - | M67: -
A68: = Change in Commercial Paper, Net | B68: - | C68: 6306 | D68: 2191 | E68: - | F68: 3852 | G68: - | H68: - | I68: - | J68: 1022 | K68: 3955 | L68: - | M68: -
A69: Long-Term Debt Issued | B69: 16896 | C69: 11960 | D69: 27114 | E69: 24954 | F69: 28662 | G69: 6969 | H69: 6963 | I69: 16091 | J69: 20393 | K69: 5465 | L69: 5228 | M69: -
A70: = Proceeds from Issuance of Term Debt, Net | B70: 16896 | C70: 11960 | D70: 27114 | E70: 24954 | F70: 28662 | G70: 6969 | H70: 6963 | I70: 16091 | J70: 20393 | K70: 5465 | L70: 5228 | M70: -
A71: Total Debt Issued | B71: 16896 | C71: 18266 | D71: 29305 | E71: 24954 | F71: 32514 | G71: 6969 | H71: 6963 | I71: 16091 | J71: 21415 | K71: 9420 | L71: 5228 | M71: 5228
A72: Short Term Debt Repaid | B72: - | C72: - | D72: - | E72: -397 | F72: - | G72: -37 | H72: -5977 | I72: -963 | J72: - | K72: - | L72: -3978 | M72: -
A73: = Change in Commercial Paper, Net | B73: - | C73: - | D73: - | E73: -397 | F73: - | G73: -37 | H73: -5977 | I73: -963 | J73: - | K73: - | L73: -3978 | M73: -
A74: Long-Term Debt Repaid | B74: - | C74: - | D74: - | E74: -2500 | F74: -3500 | G74: -6500 | H74: -8805 | I74: -12629 | J74: -8750 | K74: -9543 | L74: -11151 | M74: -
A75: = Repayments of Term Debt | B75: - | C75: - | D75: - | E75: -2500 | F75: -3500 | G75: -6500 | H75: -8805 | I75: -12629 | J75: -8750 | K75: -9543 | L75: -11151 | M75: -
A76: Total Debt Repaid | B76: - | C76: - | D76: - | E76: -2897 | F76: -3500 | G76: -6537 | H76: -14782 | I76: -13592 | J76: -8750 | K76: -9543 | L76: -15129 | M76: -9498
A78: Issuance of Common Stock | B78: 530 | C78: 730 | D78: 543 | E78: 495 | F78: 555 | G78: 669 | H78: 781 | I78: - | J78: - | K78: - | L78: - | M78: -
A79: = Proceeds from Issuance of Common Stock | B79: 530 | C79: 730 | D79: 543 | E79: 495 | F79: 555 | G79: 669 | H79: 781 | I79: - | J79: - | K79: - | L79: - | M79: -
A80: Repurchase of Common Stock | B80: -23942 | C80: -46158 | D80: -36752 | E80: -31292 | F80: -34774 | G80: -75265 | H80: -69714 | I80: -75992 | J80: -92527 | K80: -95625 | L80: -82981 | M80: -83920
A81: = Repurchase of Common Stock | B81: -22860 | C81: -45000 | D81: -35253 | E81: -29722 | F81: -32900 | G81: -72738 | H81: -66897 | I81: -72358 | J81: -85971 | K81: -89402 | L81: -77550 | M81: -
A82: + Taxes Paid Related to Net Share Settlement of Equity Awards | B82: -1082 | C82: -1158 | D82: -1499 | E82: -1570 | F82: -1874 | G82: -2527 | H82: -2817 | I82: -3634 | J82: -6556 | K82: -6223 | L82: -5431 | M82: -
A84: Common Dividends Paid | B84: -10564 | C84: -11126 | D84: -11561 | E84: -12150 | F84: -12769 | G84: -13712 | H84: -14119 | I84: -14081 | J84: -14467 | K84: -14841 | L84: -15025 | M84: -15082
A85: = Common Stock Dividends Paid | B85: -10564 | C85: -11126 | D85: -11561 | E85: -12150 | F85: -12769 | G85: -13712 | H85: - | I85: - | J85: - | K85: - | L85: - | M85: -
A86: + Cash Dividends | B86: - | C86: - | D86: - | E86: - | F86: - | G86: - | H86: -14119 | I86: -14081 | J86: -14467 | K86: -14841 | L86: -15025 | M86: -
A87: Total Dividends Paid | B87: -10564 | C87: -11126 | D87: -11561 | E87: -12150 | F87: -12769 | G87: -13712 | H87: -14119 | I87: -14081 | J87: -14467 | K87: -14841 | L87: -15025 | M87: -15082
A89: Special Dividend Paid | B89: - | C89: - | D89: - | E89: - | F89: - | G89: - | H89: - | I89: - | J89: - | K89: - | L89: - | M89: -
A90: Other Financing Activities | B90: 701 | C90: 739 | D90: 749 | E90: - | F90: - | G90: - | H90: -105 | I90: 754 | J90: 976 | K90: -160 | L90: -581 | M90: -238
A91: = Others | B91: - | C91: - | D91: - | E91: - | F91: - | G91: - | H91: -105 | I91: 754 | J91: 976 | K91: -160 | L91: -581 | M91: -
A92: + Excess Tax Benefits from Stock-based Compensation | B92: 701 | C92: 739 | D92: 749 | E92: - | F92: - | G92: - | H92: - | I92: - | J92: - | K92: - | L92: - | M92: -
A93: Cash from Financing | B93: -16379 | C93: -37549 | D93: -17716 | E93: -20890 | F93: -17974 | G93: -87876 | H93: -90976 | I93: -86820 | J93: -93353 | K93: -110749 | L93: -108488 | M93: -103510
A95: Net Change in Cash | B95: 3513 | C95: -415 | D95: 7276 | E95: -636 | F95: -195 | G95: 5624 | H95: 24311 | I95: -10435 | J95: -3860 | K95: -10952 | L95: 5760 | M95: 20000
A97: Supplemental Items
A98: Cash Interest Paid | B98: NA | C98: 339 | D98: 514 | E98: 1316 | F98: 2092 | G98: 3022 | H98: 3423 | I98: 3002 | J98: 2687 | K98: 2865 | L98: 3803 | M98: 3803
A99: Cash Taxes Paid | B99: 9128 | C99: 10026 | D99: 13252 | E99: 10444 | F99: 11591 | G99: 10417 | H99: 15263 | I99: 9501 | J99: 25385 | K99: 19573 | L99: 18679 | M99: 25106
A100: Levered Free Cash Flow | B100: 31417.375 | C100: 36375.375 | D100: 55863.625 | E100: 44058 | F100: 39624.125 | G100: 47482.25 | H100: 42914.25 | I100: 60387.375 | J100: 73295 | K100: 90215.25 | L100: 82180 | M100: 86563.125
A101: Unlevered Free Cash Flow | B101: 31502.375 | C101: 36615.375 | D101: 56321.75 | E101: 44968 | F101: 41076 | G101: 49507.25 | H101: 45149.25 | I101: 62183 | J101: 74948.125 | K101: 92047.125 | L101: 84638.125 | M101: 89021.25
A102: Change in Net Working Capital | B102: -944 | C102: -2805 | D102: -8448 | E102: -5472 | F102: -190 | G102: -2266 | H102: 2927 | I102: -10177 | J102: 1250 | K102: -7965 | L102: -1807 | M102: -2048
A103: Net Debt Issued | B103: 16896 | C103: 18266 | D103: 29305 | E103: 22057 | F103: 29014 | G103: 432 | H103: -7819 | I103: 2499 | J103: 12665 | K103: -123 | L103: -9901 | M103: -4270
A104: Filing Date | B104: 42305 | C104: 42669 | D104: 43042 | E104: 43409 | F104: 43769 | G104: 44134 | H104: 44498 | I104: 44862 | J104: 45233 | K104: 45233 | L104: 45233 | M104: 45324
A105: Restatement Type | B105: NC | C105: NC | D105: NC | E105: RS | F105: RS | G105: NC | H105: NC | I105: NC | J105: NC | K105: NC | L105: O | M105: O
A106: Calculation Type | B106: REP | C106: REP | D106: REP | E106: REP | F106: REP | G106: REP | H106: REP | I106: REP | J106: REP | K106: REP | L106: REP | M106: LTM

Sheet beta
A1: Daily | G1: Daily | J1: Weekly | P1: Weekly | S1: Average
A2: Date | B2: AAPL_Adj Close | C2: Log-return AAPL | D2: S&P 500 | E2: Log-return S&P 500 | G2: Volatility(AAPL) | H2: =_xlfn.STDEV.S(C4:C2518) -> 0.01788522 | J2: Date | K2: AAPL_Adj Close | L2: Log-return AAPL | M2: S&P 500 | N2: Log-return S&P 500 | P2: Volatility(AAPL) | Q2: =_xlfn.STDEV.S(L4:L524) -> 0.037303841 | S2: Average beta | T2: =AVERAGE(H5,Q5) -> 1.1948597
A3: 41641 | B3: 17.296661 | D3: 1831.98 | G3: Covariance | H3: =_xlfn.COVARIANCE.S(C4:C2518, E4:E2518) -> 0.00014931499 | J3: 41640 | K3: 16.887325 | M3: 1837.88 | P3: Covariance | Q3: =_xlfn.COVARIANCE.S(L4:L524,N4:N524) -> 0.00054878484 | S3: Average Volatility | T3: =AVERAGE(H7,Q7) -> 0.27646044
A4: 41642 | B4: 16.916723 | C4: =LN(B4/B3) -> -0.022210818 | D4: 1831.37 | E4: =LN(D4/D3) -> -0.00033302852 | G4: Variance(S&P) | H4: =_xlfn.VAR.S(E4:E2518) -> 0.00012573049 | J4: 41647 | K4: 17.085897 | L4: =LN(K4/K3) -> 0.011690046 | M4: 1838.88 | N4: =LN(M4/M3) -> 0.00054395719 | P4: Variance(S&P) | Q4: =_xlfn.VAR.S(N4:N524) -> 0.00045650675
A5: 41645 | B5: 17.008963 | C5: =LN(B5/B4) -> 0.0054377811 | D5: 1826.77 | E5: =LN(D5/D4) -> -0.0025149406 | G5: beta | H5: =H3/H4 -> 1.1875798 | J5: 41654 | K5: 17.169701 | L5: =LN(K5/K4) -> 0.0048928743 | M5: 1843.8 | N5: =LN(M5/M4) -> 0.0026719687 | P5: beta | Q5: =Q3/Q4 -> 1.2021396
A6: 41646 | B6: 16.887327 | C6: =LN(B6/B5) -> -0.0071769814 | D6: 1837.88 | E6: =LN(D6/D5) -> 0.0060633534 | J6: 41661 | K6: 15.838517 | L6: =LN(K6/K5) -> -0.080701502 | M6: 1792.5 | N6: =LN(M6/M5) -> -0.028217366
A7: 41647 | B7: 16.994272 | C7: =LN(B7/B6) -> 0.0063128871 | D7: 1837.49 | E7: =LN(D7/D6) -> -0.00021222353 | G7: Annualized Volatility | H7: =H2*SQRT(252) -> 0.28391907 | J7: 41668 | K7: 15.910119 | L7: =LN(K7/K6) -> 0.0045105636 | M7: 1755.2 | N7: =LN(M7/M6) -> -0.021028483 | P7: Annualized Volatility | Q7: =Q2*SQRT(52) -> 0.26900182
A8: 41648 | B8: 16.777254 | C8: =LN(B8/B7) -> -0.012852306 | D8: 1838.13 | E8: =LN(D8/D7) -> 0.00034824057 | J8: 41675 | K8: 16.759748 | L8: =LN(K8/K7) -> 0.052024737 | M8: 1819.75 | N8: =LN(M8/M7) -> 0.036116318
A9: 41649 | B9: 16.665308 | C9: =LN(B9/B8) -> -0.006694847 | D9: 1842.37 | E9: =LN(D9/D8) -> 0.0023040358 | J9: 41682 | K9: 17.175587 | L9: =LN(K9/K8) -> 0.024508956 | M9: 1840.76 | N9: =LN(M9/M8) -> 0.011479401
A10: 41652 | B10: 16.752541 | C10: =LN(B10/B9) -> 0.0052207548 | D10: 1819.2 | E10: =LN(D10/D9) -> -0.012655942 | J10: 41689 | K10: 16.422802 | L10: =LN(K10/K9) -> -0.04481828 | M10: 1845.12 | N10: =LN(M10/M9) -> 0.0023657862
A11: 41653 | B11: 17.08589 | C11: =LN(B11/B10) -> 0.019703028 | D11: 1838.88 | E11: =LN(D11/D10) -> 0.010759847 | J11: 41696 | K11: 16.71159 | L11: =LN(K11/K10) -> 0.017431756 | M11: 1873.91 | N11: =LN(M11/M10) -> 0.015482841
A12: 41654 | B12: 17.428938 | C12: =LN(B12/B11) -> 0.019878952 | D12: 1848.38 | E12: =LN(D12/D11) -> 0.0051528891 | J12: 41703 | K12: 16.864149 | L12: =LN(K12/K11) -> 0.009087517 | M12: 1867.63 | N12: =LN(M12/M11) -> -0.0033569097
A13: 41655 | B13: 17.331684 | C13: =LN(B13/B12) -> -0.0055956567 | D13: 1845.89 | E13: =LN(D13/D12) -> -0.0013480338 | J13: 41710 | K13: 16.716621 | L13: =LN(K13/K12) -> -0.0087865138 | M13: 1872.25 | N13: =LN(M13/M12) -> 0.0024706688
A14: 41656 | B14: 16.907028 | C14: =LN(B14/B13) -> -0.024806878 | D14: 1838.7 | E14: =LN(D14/D13) -> -0.0039027458 | J14: 41717 | K14: 17.144131 | L14: =LN(K14/K13) -> 0.025252405 | M14: 1865.62 | N14: =LN(M14/M13) -> -0.0035474786
A15: 41660 | B15: 17.169697 | C15: =LN(B15/B14) -> 0.015416634 | D15: 1843.8 | E15: =LN(D15/D14) -> 0.0027698592 | J15: 41724 | K15: 17.039057 | L15: =LN(K15/K14) -> -0.0061477198 | M15: 1885.52 | N15: =LN(M15/M14) -> 0.010610207
A16: 41661 | B16: 17.245996 | C16: =LN(B16/B15) -> 0.0044339729 | D16: 1844.86 | E16: =LN(D16/D15) -> 0.00057473447 | J16: 41731 | K16: 16.466213 | L16: =LN(K16/K15) -> -0.034197595 | M16: 1851.96 | N16: =LN(M16/M15) -> -0.017959107
A17: 41662 | B17: 17.392027 | C17: =LN(B17/B16) -> 0.0084318822 | D17: 1828.46 | E17: =LN(D17/D16) -> -0.0089293113 | J17: 41738 | K17: 16.293823 | L17: =LN(K17/K16) -> -0.010524506 | M17: 1842.98 | N17: =LN(M17/M16) -> -0.004860711
A18: 41663 | B18: 17.075893 | C18: =LN(B18/B17) -> -0.01834418 | D18: 1790.29 | E18: =LN(D18/D17) -> -0.021096465 | J18: 41745 | K18: 16.726053 | L18: =LN(K18/K17) -> 0.026181485 | M18: 1879.55 | N18: =LN(M18/M17) -> 0.01964856
A19: 41666 | B19: 17.214417 | C19: =LN(B19/B18) -> 0.0080795276 | D19: 1781.56 | E19: =LN(D19/D18) -> -0.0048882329 | J19: 41752 | K19: 18.633327 | L19: =LN(K19/K18) -> 0.10798419 | M19: 1878.33 | N19: =LN(M19/M18) -> -0.00064930229
... A524: 42397 | B524: 21.38743 | C524: =LN(B524/B523) -> 0.0071465747 | D524: 1893.36 | E524: =LN(D524/D523) -> 0.0055133325 | J524: 45287 | K524: 192.28464 | L524: =LN(K524/K523) -> -0.0026972976 | M524: 4769.83 | N524: =LN(M524/M523) -> -0.0010309517
A525: 42398 | B525: 22.126173 | C525: =LN(B525/B524) -> 0.03395784 | D525: 1940.24 | E525: =LN(D525/D524) -> 0.024458648
A526: 42401 | B526: 21.919329 | C526: =LN(B526/B525) -> -0.0093923561 | D526: 1939.38 | E526: =LN(D526/D525) -> -0.0004433424
A527: 42402 | B527: 21.476076 | C527: =LN(B527/B526) -> -0.020429279 | D527: 1903.03 | E527: =LN(D527/D526) -> -0.018920982
A528: 42403 | B528: 21.901146 | C528: =LN(B528/B527) -> 0.019599393 | D528: 1912.53 | E528: =LN(D528/D527) -> 0.0049796201
A529: 42404 | B529: 22.077126 | C529: =LN(B529/B528) -> 0.0080030857 | D529: 1915.45 | E529: =LN(D529/D528) -> 0.0015256091
A530: 42405 | B530: 21.487484 | C530: =LN(B530/B529) -> -0.027071424 | D530: 1880.05 | E530: =LN(D530/D529) -> -0.01865421
A531: 42408 | B531: 21.713743 | C531: =LN(B531/B530) -> 0.010474752 | D531: 1853.44 | E531: =LN(D531/D530) -> -0.014255
A532: 42409 | B532: 21.709164 | C532: =LN(B532/B531) -> -0.00021090251 | D532: 1852.21 | E532: =LN(D532/D531) -> -0.00066385117
A533: 42410 | B533: 21.544619 | C533: =LN(B533/B532) -> -0.0076083886 | D533: 1851.86 | E533: =LN(D533/D532) -> -0.00018898131
A534: 42411 | B534: 21.414351 | C534: =LN(B534/B533) -> -0.0060647822 | D534: 1829.08 | E534: =LN(D534/D533) -> -0.012377431
A535: 42412 | B535: 21.480627 | C535: =LN(B535/B534) -> 0.0030901544 | D535: 1864.78 | E535: =LN(D535/D534) -> 0.019329975
A536: 42416 | B536: 22.08626 | C536: =LN(B536/B535) -> 0.027804237 | D536: 1895.58 | E536: =LN(D536/D535) -> 0.016381777
... A2518: 45289 | B2518: 192.28464 | C2518: =LN(B2518/B2517) -> -0.0054388735 | D2518: 4769.83 | E2518: =LN(D2518/D2517) -> -0.002830473

Sheet WACC
A2: 10y Avg beta | B2: =beta!T2 -> 1.1948597
A4: rf | B4: 0.0443 | C4: 45366 | D4: (30-year US Treasury bond yield, found at treasury.gov)
A5: rm-rf(risk premium) | B5: 0.06
A6: r(E) | B6: =B4+B2*B5 -> 0.11599158 | C6: by CAPM: r(E) = rf + beta * risk premium
A7: r(D) | B7: 0.05026 | C7: 45366 | D7: YTW of 2053/5/10 AAPL corporate bond rated AA+
A9: Equity Value(Market Cap) | B9: ='Key Stats'!B53 -> 2665577.5 | C9: 45366
A10: Net Debt | B10: =BS!Q20 -> 32942 | C10: FY24Q1
A12: E/V | B12: =B9/(B9+B10) -> 0.98779257
A13: D/V | B13: =B10/(B9+B10) -> 0.012207434
A15: Effective Tax Rate | B15: =IS!O84 -> 0.1491958 | C15: 5-yr avg
A17: WACC | B17: =B12*B6+B13*B7*(1-B15) -> 0.11509763

Sheet Segment_Q
B1: FY1Q15 | C1: FY2Q15 | D1: FY3Q15 | E1: FY4Q15 | F1: FY1Q16 | G1: FY2Q16 | H1: FY3Q16 | I1: FY4Q16 | J1: FY1Q17 | K1: FY2Q17 | L1: FY3Q17 | M1: FY4Q17 | N1: FY1Q18 | O1: FY2Q18 | P1: FY3Q18 | Q1: FY4Q18 | R1: FY1Q19 | S1: FY2Q19 | T1: FY3Q19 | U1: FY4Q19 | V1: FY1Q20 | W1: FY2Q20 | X1: FY3Q20 | Y1: FY4Q20 | Z1: FY1Q21 | AA1: FY2Q21 | AB1: FY3Q21 | AC1: FY4Q21 | AD1: FY1Q22 | AE1: FY2Q22 | AF1: FY3Q22 | AG1: FY4Q22 | AH1: FY1Q23 | AI1: FY2Q23 | AJ1: FY3Q23 | AK1: FY4Q23 | AL1: FY1Q24 | AM1: FY2Q24E | AN1: FY3Q24E | AO1: FY4Q24E | AP1: FY1Q25E | AQ1: FY2Q25E | AR1: FY3Q25E | AS1: FY4Q25E
A2: iPhone | B2: 51182 | C2: 40282 | D2: 31368 | E2: ='[1]Segment Sales-Annual'!F2-SUM('[1]Segment Sales-Qty'!B2:D2) -> 32209 | F2: 51635 | G2: 32857 | H2: 24048 | I2: ='[1]Segment Sales-Annual'!G2-SUM('[1]Segment Sales-Qty'!F2:H2) -> 28160 | J2: 54378 | K2: 33249 | L2: 24846 | M2: ='[1]Segment Sales-Annual'!H2-SUM('[1]Segment Sales-Qty'!J2:L2) -> 26864 | N2: 61104 | O2: 37559 | P2: 29470 | Q2: ='[1]Segment Sales-Annual'!I2-SUM('[1]Segment Sales-Qty'!N2:P2) -> 36755 | R2: 51982 | S2: 31051 | T2: 25986 | U2: ='[1]Segment Sales-Annual'!J2-SUM('[1]Segment Sales-Qty'!R2:T2) -> 33362 | V2: 55957 | W2: 28962 | X2: 26418 | Y2: ='[1]Segment Sales-Annual'!K2-SUM('[1]Segment Sales-Qty'!V2:X2) -> 26444 | Z2: 65597 | AA2: 47938 | AB2: 39570 | AC2: ='[1]Segment Sales-Annual'!L2-SUM('[1]Segment Sales-Qty'!Z2:AB2) -> 38868 | AD2: 71628 | AE2: 50570 | AF2: 40665 | AG2: 42626 | AH2: 65775 | AI2: 51334 | AJ2: 39669 | AK2: =Segment_A!N2-SUM(Segment_Q!AH2:AJ2) -> 43805 | AL2: 69702 | AM2: =AL2*(1+AM3) -> 52276.5 | AN2: =AM2*(1+AN3) -> 43403.911 | AO2: =AN2*(1+AO3) -> 47046.147 | AP2: =AO2*(1+AP3) -> 78265.744 | AQ2: =AP2*(1+AQ3) -> 54548.546 | AR2: =AQ2*(1+AR3) -> 45218.271 | AS2: =AR2*(1+AS3) -> 47204.66
A3: QoQ | C3: =C2/B2-1 -> -0.2129655 | D3: =D2/C2-1 -> -0.22128991 | E3: =E2/D2-1 -> 0.026810763 | F3: =F2/E2-1 -> 0.60312335 | G3: =G2/F2-1 -> -0.36366805 | H3: =H2/G2-1 -> -0.26810117 | I3: =I2/H2-1 -> 0.17099135 | J3: =J2/I2-1 -> 0.93103693 | ... M3: =M2/L2-1 -> 0.081220317 | O3: =O2/N2-1 -> -0.38532666 | P3: =P2/O2-1 -> -0.21536782 | Q3: =Q2/P2-1 -> 0.24720054 | R3: =R2/Q2-1 -> 0.41428377 | S3: =S2/R2-1 -> -0.40265861 | T3: =T2/S2-1 -> -0.16311874 | U3: =U2/T2-1 -> 0.28384515 | V3: =V2/U2-1 -> 0.67726755 | ... AL3: =AL2/AK2-1 -> 0.59118822 | AM3: =-25% -> -0.25 | AN3: =AVERAGE(AJ3,AF3,AB3,X3,T3) -> -0.16972424 | AO3: =AVERAGE(AK3,AG3,AC3,Y3,U3) -> 0.083914935 | AP3: =AVERAGE(AL3,AH3,AD3,V3) -> 0.6635952 | AQ3: =AVERAGE(AM3,AI3,AE3,AA3,W3) -> -0.30303421 | AR3: =AVERAGE(AN3,AJ3,AF3,AB3,X3) -> -0.17104534 | AS3: =AVERAGE(AO3,AK3,AG3,AC3,Y3) -> 0.043928892
A4: YoY | F4: =F2/B2-1 -> 0.0088507678 | G4: =G2/C2-1 -> -0.18432551 | H4: =H2/D2-1 -> -0.23335884 | I4: =I2/E2-1 -> -0.12571021 | J4: =J2/F2-1 -> 0.053122882 | K4: =K2/G2-1 -> 0.011930487 | L4: =L2/H2-1 -> 0.033183633 | M4: =M2/I2-1 -> -0.046022727 | R4: =R2/N2-1 -> -0.14928646 | S4: =S2/O2-1 -> -0.17327405 | T4: =T2/P2-1 -> -0.11822192 | U4: =U2/Q2-1 -> -0.092313971 | V4: =V2/R2-1 -> 0.076468778 | W4: =W2/S2-1 -> -0.067276416 | X4: =X2/T2-1 -> 0.016624336 | Y4: =Y2/U2-1 -> -0.20736167 | ... AS4: =AS2/AO2-1 -> 0.0033693088
A5: Proportion | B5: =B2/B$32 -> 0.68609499 | C5: =C2/C$32 -> 0.69439752 | D5: =D2/D$32 -> 0.63235561 | E5: =E2/E$32 -> 0.62540533 | F5: =F2/F$32 -> 0.68055409 | G5: =G2/G$32 -> 0.64990011 | H5: =H2/H$32 -> 0.56773219 | I5: =I2/I$32 -> 0.60104158 | ... AS5: =AS2/AS$32 -> 0.45117803
A7: Mac | B7: 6944 | C7: 5615 | D7: 6030 | E7: ='[1]Segment Sales-Annual'!F3-SUM('[1]Segment Sales-Qty'!B7:D7) -> 6882 | F7: 6746 | G7: 5107 | H7: 5239 | I7: ='[1]Segment Sales-Annual'!G3-SUM('[1]Segment Sales-Qty'!F7:H7) -> 5739 | J7: 7244 | K7: 5844 | L7: 5592 | M7: ='[1]Segment Sales-Annual'!H3-SUM('[1]Segment Sales-Qty'!J7:L7) -> 6889 | N7: 6824 | O7: 5776 | P7: 5258 | Q7: ='[1]Segment Sales-Annual'!I3-SUM('[1]Segment Sales-Qty'!N7:P7) -> 7340 | R7: 7416 | S7: 5513 | T7: 5820 | U7: ='[1]Segment Sales-Annual'!J3-SUM('[1]Segment Sales-Qty'!R7:T7) -> 6991 | V7: 7160 | W7: 5351 | X7: 7079 | Y7: ='[1]Segment Sales-Annual'!K3-SUM('[1]Segment Sales-Qty'!V7:X7) -> 9032 | Z7: 8675 | AA7: 9102 | AB7: 8235 | AC7: ='[1]Segment Sales-Annual'!L3-SUM('[1]Segment Sales-Qty'!Z7:AB7) -> 9178 | AD7: 10852 | AE7: 10435 | AF7: 7382 | AG7: 11508 | AH7: 7735 | AI7: 7168 | AJ7: 6840 | AK7: =Segment_A!N3-SUM(Segment_Q!AH7:AJ7) -> 7614 | AL7: 7780 | AM7: =AL7*(1+AM8) -> 6890.3285 | AN7: =AM7*(1+AN8) -> 6814.5777 | AO7: =AN7*(1+AO8) -> 8536.8742 | AP7: =AO7*(1+AP8) -> 8299.521 | AQ7: =AP7*(1+AQ8) -> 7586.5678 | AR7: =AQ7*(1+AR8) -> 7401.9877 | AS7: =AR7*(1+AS8) -> 9349.0358
A8: QoQ | C8: =C7/B7-1 -> -0.19138825 | D8: =D7/C7-1 -> 0.073909172 | E8: =E7/D7-1 -> 0.14129353 | F8: =F7/E7-1 -> -0.019761697 | G8: =G7/F7-1 -> -0.24295879 | H8: =H7/G7-1 -> 0.025846877 | I8: =I7/H7-1 -> 0.095438061 | J8: =J7/I7-1 -> 0.26224081 | ... M8: =M7/L7-1 -> 0.23193848 | O8: =O7/N7-1 -> -0.15357562 | P8: =P7/O7-1 -> -0.08968144 | Q8: =Q7/P7-1 -> 0.39596805 | R8: =R7/Q7-1 -> 0.010354223 | S8: =S7/R7-1 -> -0.25660734 | T8: =T7/S7-1 -> 0.055686559 | U8: =U7/T7-1 -> 0.20120275 | V8: =V7/U7-1 -> 0.024173938 | ... AL8: =AL7/AK7-1 -> 0.021801944 | AM8: =AVERAGE(AI8,AE8,AA8,W8,S8) -> -0.11435367 | AN8: =AVERAGE(AJ8,AF8,AB8,X8,T8) -> -0.010993788 | AO8: =AVERAGE(AK8,AG8,AC8,Y8,U8) -> 0.25273708 | AP8: =AVERAGE(AL8,AH8,AD8,Z8,V8) -> -0.02780329 | AQ8: =AVERAGE(AM8,AI8,AE8,AA8,W8) -> -0.085902932 | AR8: =AVERAGE(AN8,AJ8,AF8,AB8,X8) -> -0.024329857 | AS8: =AVERAGE(AO8,AK8,AG8,AC8,Y8) -> 0.26304395
A9: YoY | F9: =F7/B7-1 -> -0.028513825 | G9: =G7/C7-1 -> -0.09047195 | H9: =H7/D7-1 -> -0.13117745 | I9: =I7/E7-1 -> -0.16608544 | J9: =J7/F7-1 -> 0.073821524 | K9: =K7/G7-1 -> 0.14431173 | L9: =L7/H7-1 -> 0.067379271 | M9: =M7/I7-1 -> 0.20038334 | R9: =R7/N7-1 -> 0.086752638 | S9: =S7/O7-1 -> -0.045533241 | T9: =T7/P7-1 -> 0.10688475 | U9: =U7/Q7-1 -> -0.047547684 | V9: =V7/R7-1 -> -0.034519957 | W9: =W7/S7-1 -> -0.02938509 | X9: =X7/T7-1 -> 0.21632302 | Y9: =Y7/U7-1 -> 0.29194679 | ... AS9: =AS7/AO7-1 -> 0.095135712
A10: Proportion | B10: =B7/B$32 -> 0.093084358 | C10: =C7/C$32 -> 0.096793656 | D10: =D7/D$32 -> 0.12156033 | E10: =E7/E$32 -> 0.13362847 | F10: =F7/F$32 -> 0.088912906 | G10: =G7/G$32 -> 0.1010147 | H10: =H7/H$32 -> 0.12368384 | I10: =I7/I$32 -> 0.1224921 | ... AS10: =AS7/AS$32 -> 0.089357269
A12: iPad | B12: 8985 | C12: 5428 | D12: 4538 | E12: ='[1]Segment Sales-Annual'!F4-SUM('[1]Segment Sales-Qty'!B12:D12) -> 4276 | F12: 7084 | G12: 4413 | H12: 4876 | I12: ='[1]Segment Sales-Annual'!G4-SUM('[1]Segment Sales-Qty'!F12:H12) -> 4255 | J12: 5533 | K12: 3889 | L12: 4969 | M12: ='[1]Segment Sales-Annual'!H4-SUM('[1]Segment Sales-Qty'!J12:L12) -> 4411 | N12: 5755 | O12: 4008 | P12: 4634 | Q12: ='[1]Segment Sales-Annual'!I4-SUM('[1]Segment Sales-Qty'!N12:P12) -> 3983 | R12: 6729 | S12: 4872 | T12: 5023 | U12: ='[1]Segment Sales-Annual'!J4-SUM('[1]Segment Sales-Qty'!R12:T12) -> 4656 | V12: 5977 | W12: 4368 | X12: 6582 | Y12: ='[1]Segment Sales-Annual'!K4-SUM('[1]Segment Sales-Qty'!V12:X12) -> 6797 | Z12: 8435 | AA12: 7807 | AB12: 7368 | AC12: ='[1]Segment Sales-Annual'!L4-SUM('[1]Segment Sales-Qty'!Z12:AB12) -> 8252 | AD12: 7248 | AE12: 7646 | AF12: 7224 | AG12: 7174 | AH12: 9396 | AI12: 6670 | AJ12: 5791 | AK12: =Segment_A!N4-SUM(Segment_Q!AH12:AJ12) -> 6443 | AL12: 7023 | AM12: =AL12*(1+AM13) -> 5822.3034 | AN12: =AM12*(1+AN13) -> 6165.4159 | AO12: =AN12*(1+AO13) -> 6393.8401 | AP12: =AO12*(1+AP13) -> 7420.4234 | AQ12: =AP12*(1+AQ13) -> 6307.6145 | AR12: =AQ12*(1+AR13) -> 6714.5704 | AS12: =AR12*(1+AS13) -> 7111.2128
A13: QoQ | C13: =C12/B12-1 -> -0.39588203 | D13: =D12/C12-1 -> -0.16396463 | E13: =E12/D12-1 -> -0.057734685 | F13: =F12/E12-1 -> 0.65668849 | G13: =G12/F12-1 -> -0.37704687 | H13: =H12/G12-1 -> 0.10491729 | I13: =I12/H12-1 -> -0.12735849 | J13: =J12/I12-1 -> 0.30035253 | ... M13: =M12/L12-1 -> -0.11229624 | O13: =O12/N12-1 -> -0.30356212 | P13: =P12/O12-1 -> 0.15618762 | Q13: =Q12/P12-1 -> -0.14048338 | R13: =R12/Q12-1 -> 0.68943008 | S13: =S12/R12-1 -> -0.27596968 | T13: =T12/S12-1 -> 0.030993432 | U13: =U12/T12-1 -> -0.073063906 | V13: =V12/U12-1 -> 0.28371993 | ... AL13: =AL12/AK12-1 -> 0.090020177 | AM13: =AVERAGE(AI13,AE13,AA13,W13,S13) -> -0.17096634 | AN13: =AVERAGE(AJ13,AF13,AB13,X13,T13) -> 0.058930722 | AO13: =AVERAGE(AK13,AG13,AC13,Y13,U13) -> 0.03704927 | AP13: =AVERAGE(AL13,AH13,AD13,Z13,V13) -> 0.16055818 | AQ13: =AVERAGE(AM13,AI13,AE13,AA13,W13) -> -0.14996568 | AR13: =AVERAGE(AN13,AJ13,AF13,AB13,X13) -> 0.06451818 | AS13: =AVERAGE(AO13,AK13,AG13,AC13,Y13) -> 0.059071905
A14: YoY | F14: =F12/B12-1 -> -0.21157485 | G14: =G12/C12-1 -> -0.18699337 | H14: =H12/D12-1 -> 0.074482151 | I14: =I12/E12-1 -> -0.0049111319 | J14: =J12/F12-1 -> -0.2189441 | K14: =K12/G12-1 -> -0.11874009 | L14: =L12/H12-1 -> 0.019073011 | M14: =M12/I12-1 -> 0.03666275 | R14: =R12/N12-1 -> 0.16924414 | S14: =S12/O12-1 -> 0.21556886 | T14: =T12/P12-1 -> 0.083944756 | U14: =U12/Q12-1 -> 0.16896811 | V14: =V12/R12-1 -> -0.11175509 | W14: =W12/S12-1 -> -0.10344828 | X14: =X12/T12-1 -> 0.31037229 | Y14: =Y12/U12-1 -> 0.45983677 | ... AS14: =AS12/AO12-1 -> 0.11219748
A15: Proportion | B15: =B12/B$32 -> 0.12044397 | C15: =C12/C$32 -> 0.093570074 | D15: =D12/D$32 -> 0.091482713 | E15: =E12/E$32 -> 0.083027514 | F15: =F12/F$32 -> 0.093367777 | G15: =G12/G$32 -> 0.087287616 | H15: =H12/H$32 -> 0.11511403 | I15: =I12/I$32 -> 0.090817895 | ... AS15: =AS12/AS$32 -> 0.067968352
A17: Wearables, Home and Accessories | M17: =M32-(M2+M7+M12+M22) -> 3194 | N17: 5481 | O17: 3944 | P17: 3733 | Q17: ='[1]Segment Sales-Annual'!I5-SUM('[1]Segment Sales-Qty'!N17:P17) -> 4223 | R17: 7308 | S17: 5129 | T17: 5525 | U17: ='[1]Segment Sales-Annual'!J5-SUM('[1]Segment Sales-Qty'!R17:T17) -> 6520 | V17: 10010 | W17: 6284 | X17: 6450 | Y17: ='[1]Segment Sales-Annual'!K5-SUM('[1]Segment Sales-Qty'!V17:X17) -> 7876 | Z17: 12971 | AA17: 7836 | AB17: 8775 | AC17: ='[1]Segment Sales-Annual'!L5-SUM('[1]Segment Sales-Qty'!Z17:AB17) -> 8785 | AD17: 14701 | AE17: 8806 | AF17: 8084 | AG17: 9650 | AH17: 13482 | AI17: 8757 | AJ17: 8284 | AK17: =Segment_A!N5-SUM(Segment_Q!AH17:AJ17) -> 9322 | AL17: 11953 | AM17: =AL17*(1+AM18)+AM39 -> 8347.5162 | AN17: =AM17*(1+AN18)+AN39 -> 8863.5183 | AO17: =AN17*(1+AO18)+AO39 -> 10512.228 | AP17: =AO17*(1+AP18)+AP39 -> 16211.786 | AQ17: =AP17*(1+AQ18) -> 10106.042 | AR17: =AQ17*(1+AR18) -> 10162.1 | AS17: =AR17*(1+AS18) -> 11555.343
A18: QoQ | O18: =O17/N17-1 -> -0.28042328 | P18: =P17/O17-1 -> -0.053498986 | Q18: =Q17/P17-1 -> 0.13126172 | R18: =R17/Q17-1 -> 0.73052332 | S18: =S17/R17-1 -> -0.29816639 | T18: =T17/S17-1 -> 0.077208033 | U18: =U17/T17-1 -> 0.1800905 | V18: =V17/U17-1 -> 0.53527607 | ... AL18: =AL17/AK17-1 -> 0.28223557 | AM18: =AVERAGE(AI18,AE18,AA18,W18,S18) -> -0.36354754 | AN18: =AVERAGE(AJ18,AF18,AB18,X18,T18) -> 0.017490478 | AO18: =AVERAGE(AK18,AG18,AC18,Y18,U18) -> 0.14426663 | AP18: =AVERAGE(AL18,AH18,AD18,Z18,V18) -> 0.50698653 | AQ18: =AVERAGE(AM18,AI18,AE18,AA18,W18) -> -0.37662377 | AR18: =AVERAGE(AN18,AJ18,AF18,AB18,X18) -> 0.0055469672 | AS18: =AVERAGE(AO18,AK18,AG18,AC18,Y18) -> 0.13710185
A19: YoY | R19: =R17/N17-1 -> 0.33333333 | S19: =S17/O17-1 -> 0.30045639 | T19: =T17/P17-1 -> 0.48004286 | U19: =U17/Q17-1 -> 0.54392612 | V19: =V17/R17-1 -> 0.3697318 | W19: =W17/S17-1 -> 0.2251901 | X19: =X17/T17-1 -> 0.16742081 | Y19: =Y17/U17-1 -> 0.20797546 | ... AS19: =AS17/AO17-1 -> 0.099228695
A20: Proportion | N20: =N17/N32 -> 0.062077401 | O20: =O17/O32 -> 0.064510853 | P20: =P17/P32 -> 0.070083545 | Q20: =Q17/Q32 -> 0.067138315 | R20: =R17/R32 -> 0.086680109 | S20: =S17/S32 -> 0.08840817 | T20: =T17/T32 -> 0.10267799 | U20: =U17/U32 -> 0.10181137 | ... AL20: =AL17/AL32 -> 0.099962367 | AM20: =AM17/AM$32 -> 0.085733085 | AN20: =AN17/AN$32 -> 0.099150984 | AO20: =AO17/AO$32 -> 0.10731253 | AP20: =AP17/AP$32 -> 0.11822861 | AQ20: =AQ17/AQ$32 -> 0.094923997 | AR20: =AR17/AR$32 -> 0.1041482 | AS20: =AS17/AS$32 -> 0.11044496
A22: Services | B22: 4799 | C22: 4996 | D22: 5028 | E22: ='[1]Segment Sales-Annual'!F6-SUM('[1]Segment Sales-Qty'!B22:D22) -> 5086 | F22: 6056 | G22: 5991 | H22: 5976 | I22: ='[1]Segment Sales-Annual'!G6-SUM('[1]Segment Sales-Qty'!F22:H22) -> 6325 | J22: 7172 | K22: 7041 | L22: 7266 | M22: ='[1]Segment Sales-Annual'!H6-SUM('[1]Segment Sales-Qty'!J22:L22) -> 11221 | N22: 9129 | O22: 9850 | P22: 10170 | Q22: ='[1]Segment Sales-Annual'!I6-SUM('[1]Segment Sales-Qty'!N22:P22) -> 10599 | R22: 10875 | S22: 11450 | T22: 11455 | U22: ='[1]Segment Sales-Annual'!J6-SUM('[1]Segment Sales-Qty'!R22:T22) -> 12511 | V22: 12715 | W22: 13348 | X22: 13156 | Y22: ='[1]Segment Sales-Annual'!K6-SUM('[1]Segment Sales-Qty'!V22:X22) -> 14549 | Z22: 15761 | AA22: 16901 | AB22: 17486 | AC22: ='[1]Segment Sales-Annual'!L6-SUM('[1]Segment Sales-Qty'!Z22:AB22) -> 18277 | AD22: 19516 | AE22: 19821 | AF22: 19604 | AG22: 19188 | AH22: 20766 | AI22: 20907 | AJ22: 21213 | AK22: =Segment_A!N6-SUM(Segment_Q!AH22:AJ22) -> 22314 | AL22: 23117 | AM22: =AL22*(1+AM23) -> 24029.686 | AN22: =AM22*(1+AN23) -> 24146.731 | AO22: =AN22*(1+AO23) -> 25469.915 | AP22: =AO22*(1+AP23) -> 26924.887 | AQ22: =AP22*(1+AQ23) -> 27915.796 | AR22: =AQ22*(1+AR23) -> 28076.525 | AS22: =AR22*(1+AS23) -> 29405.101
A23: QoQ | C23: =C22/B22-1 -> 0.041050219 | D23: =D22/C22-1 -> 0.0064051241 | E23: =E22/D22-1 -> 0.011535402 | F23: =F22/E22-1 -> 0.19071962 | G23: =G22/F22-1 -> -0.010733157 | H23: =H22/G22-1 -> -0.0025037556 | I23: =I22/H22-1 -> 0.058400268 | J23: =J22/I22-1 -> 0.13391304 | ... M23: =M22/L22-1 -> 0.54431599 | O23: =O22/N22-1 -> 0.078979078 | P23: =P22/O22-1 -> 0.03248731 | Q23: =Q22/P22-1 -> 0.042182891 | R23: =R22/Q22-1 -> 0.026040192 | S23: =S22/R22-1 -> 0.052873563 | T23: =T22/S22-1 -> 0.00043668122 | U23: =U22/T22-1 -> 0.092186818 | V23: =V22/U22-1 -> 0.016305651 | ... AL23: =AL22/AK22-1 -> 0.035986376 | AM23: =AVERAGE(AI23,AE23,AA23,W23,S23) -> 0.039481173 | AN23: =AVERAGE(AJ23,AF23,AB23,X23,T23) -> 0.0048708204 | AO23: =AVERAGE(AK23,AG23,AC23,Y23,U23) -> 0.054797646 | AP23: =AVERAGE(AL23,AH23,AD23,Z23,V23) -> 0.057125148 | AQ23: =AVERAGE(AM23,AI23,AE23,AA23,W23) -> 0.036802695 | AR23: =AVERAGE(AN23,AJ23,AF23,AB23,X23) -> 0.0057576483 | AS23: =AVERAGE(AO23,AK23,AG23,AC23,Y23) -> 0.047319812
A24: YoY | F24: =F22/B22-1 -> 0.26192957 | G24: =G22/C22-1 -> 0.19915933 | H24: =H22/D22-1 -> 0.18854415 | I24: =I22/E22-1 -> 0.24360991 | J24: =J22/F22-1 -> 0.18428005 | K24: =K22/G22-1 -> 0.17526289 | L24: =L22/H22-1 -> 0.21586345 | M24: =M22/I22-1 -> 0.77407115 | R24: =R22/N22-1 -> 0.19125863 | S24: =S22/O22-1 -> 0.16243655 | T24: =T22/P22-1 -> 0.12635202 | U24: =U22/Q22-1 -> 0.18039438 | V24: =V22/R22-1 -> 0.1691954 | W24: =W22/S22-1 -> 0.16576419 | X24: =X22/T22-1 -> 0.14849411 | Y24: =Y22/U22-1 -> 0.16289665 | ... AS24: =AS22/AO22-1 -> 0.15450332
A25: Proportion | B25: =B22/B$32 -> 0.064330621 | C25: =C22/C$32 -> 0.086123082 | D25: =D22/D$32 -> 0.10136075 | E25: =E22/E$32 -> 0.098755364 | F25: =F22/F$32 -> 0.079818642 | G25: =G22/G$32 -> 0.11849991 | H25: =H22/H$32 -> 0.14108315 | I25: =I22/I$32 -> 0.13499957 | ... AS25: =AS22/AS$32 -> 0.28105139
A27: Other Products | B27: 2689 | C27: 1689 | D27: 2641 | E27: ='[1]Segment Sales-Annual'!F7-SUM('[1]Segment Sales-Qty'!B27:D27) -> 3048 | F27: 4351 | G27: 2189 | H27: 2219 | I27: ='[1]Segment Sales-Annual'!G7-SUM('[1]Segment Sales-Qty'!F27:H27) -> 2373 | J27: 4024 | K27: 2873 | L27: 2735
A28: QoQ | C28: =C27/B27-1 -> -0.37188546 | D28: =D27/C27-1 -> 0.56364713 | E28: =E27/D27-1 -> 0.15410829 | F28: =F27/E27-1 -> 0.42749344 | G28: =G27/F27-1 -> -0.49689726 | H28: =H27/G27-1 -> 0.013704888 | I28: =I27/H27-1 -> 0.069400631 | J28: =J27/I27-1 -> 0.69574378 | ... L28: =L27/K27-1 -> -0.048033415
A29: YoY | F29: =F27/B27-1 -> 0.61807363 | G29: =G27/C27-1 -> 0.29603316 | H29: =H27/D27-1 -> -0.15978796 | I29: =I27/E27-1 -> -0.22145669 | J29: =J27/F27-1 -> -0.075155137 | K29: =K27/G27-1 -> 0.31247145 | L29: =L27/H27-1 -> 0.23253718
A30: Proportion | B30: =B27/B$32 -> 0.03604606 | C30: =C27/C$32 -> 0.02911567 | D30: =D27/D$32 -> 0.053240601 | E30: =E27/E$32 -> 0.059183317 | F30: =F27/F$32 -> 0.057346584 | G30: =G27/G$32 -> 0.043297664 | H30: =H27/H$32 -> 0.052386798 | I30: =I27/I$32 -> 0.050648852 | ... L30: =L27/L$32 -> 0.060231677
A32: Net Sales | B32: =B2+B7+B12+B17+B22+B27 -> 74599 | C32: =C2+C7+C12+C17+C22+C27 -> 58010 | D32: =D2+D7+D12+D17+D22+D27 -> 49605 | E32: =E2+E7+E12+E17+E22+E27 -> 51501 | F32: =F2+F7+F12+F17+F22+F27 -> 75872 | G32: =G2+G7+G12+G17+G22+G27 -> 50557 | H32: =H2+H7+H12+H17+H22+H27 -> 42358 | I32: =I2+I7+I12+I17+I22+I27 -> 46852 | ... L32: =L2+L7+L12+L17+L22+L27 -> 45408 | M32: ='[1]Segment Sales-Annual'!H8-SUM('[1]Segment Sales-Qty'!J32:L32) -> 52579 | N32: =N2+N7+N12+N17+N22+N27 -> 88293 | O32: =O2+O7+O12+O17+O22+O27 -> 61137 | P32: =P2+P7+P12+P17+P22+P27 -> 53265 | Q32: =Q2+Q7+Q12+Q17+Q22+Q27 -> 62900 | R32: =R2+R7+R12+R17+R22+R27 -> 84310 | S32: =S2+S7+S12+S17+S22+S27 -> 58015 | T32: =T2+T7+T12+T17+T22+T27 -> 53809 | U32: =U2+U7+U12+U17+U22+U27 -> 64040 | ... AS32: =AS2+AS7+AS12+AS17+AS22+AS27 -> 104625.35
A33: QoQ | O33: =O32/N32-1 -> -0.30756685 | P33: =P32/O32-1 -> -0.12876 | Q33: =Q32/P32-1 -> 0.18088801 | R33: =R32/Q32-1 -> 0.34038156 | S33: =S32/R32-1 -> -0.31188471 | T33: =T32/S32-1 -> -0.072498492 | U33: =U32/T32-1 -> 0.19013548 | V33: =V32/U32-1 -> 0.43377577 | ... AS33: =AS32/AR32-1 -> 0.072272708
A34: YoY | R34: =R32/N32-1 -> -0.045111164 | S34: =S32/O32-1 -> -0.051065639 | T34: =T32/P32-1 -> 0.010213086 | U34: =U32/Q32-1 -> 0.018124006 | V34: =V32/R32-1 -> 0.089064168 | W34: =W32/S32-1 -> 0.0051366026 | X34: =X32/T32-1 -> 0.10920106 | Y34: =Y32/U32-1 -> 0.010274828 | ... AS34: =AS32/AO32-1 -> 0.068052431
AL36: Vision Pro
AL37: Shipment(mn) | AM37: 0.2 | AN37: 0.1 | AO37: 0.1 | AP37: 0.1 | AQ37: (Consensus shipment of appox. 500k in CY2024, with FY2Q24 200k)
AL38: Unit Price(USD) | AM38: 3700 | AN38: 3700 | AO38: 3700 | AP38: 3700 | AQ38: (Avg Price: take 512GB)
AL39: Rev Contribution | AM39: =AM37*AM38 -> 740 | AN39: =AN37*AN38 -> 370 | AO39: =AO37*AO38 -> 370 | AP39: =AP37*AP38 -> 370 | AQ39: (Added to WH&A)
U41: 4Q19 | V41: 1Q20 | W41: 2Q20 | X41: 3Q20 | Y41: 4Q20 | Z41: 1Q21 | AA41: 2Q21 | AB41: 3Q21 | AC41: 4Q21 | AD41: 1Q22 | AE41: 2Q22 | AF41: 3Q22 | AG41: 4Q22 | AH41: 1Q23 | AI41: 2Q23 | AJ41: 3Q23 | AK41: 4Q23 | AL41: 1Q24
T42: Service Rev | U42: 12511 | V42: 12715 | W42: 13348 | X42: 13156 | Y42: 14549 | Z42: 15761 | AA42: 16901 | AB42: 17486 | AC42: 18277 | AD42: 19516 | AE42: 19821 | AF42: 19604 | AG42: 19188 | AH42: 20766 | AI42: =AI22 -> 20907 | AJ42: =AJ22 -> 21213 | AK42: =AK22 -> 22314 | AL42: =AL22 -> 23117
T43: Subscription Base | U43: 450 | V43: 480 | W43: 515 | X43: 550 | Y43: 585 | Z43: 620 | AA43: 660 | AB43: 700 | AC43: 745 | AD43: 785 | AE43: 825 | AF43: 860 | AG43: 900 | AH43: 935 | AI43: 975 | AJ43: =AI43+150 -> 1125
T44: (From Earnings Transcript) | AJ44: plus 150 than 2Q | AK44: more than 1b | AL44: more than 1b

Sheet Segment_A
A1: Sales | B1: FY2011 | C1: FY2012 | D1: FY2013 | E1: FY2014 | F1: FY2015 | G1: FY2016 | H1: FY2017 | I1: FY2018 | J1: FY2019 | K1: FY2020 | L1: FY2021 | M1: FY2022 | N1: FY2023 | O1: FY2024E | P1: FY2025E | Q1: FY2026E | R1: FY2027E | S1: FY2028E | T1: FY2029E
A2: iPhone | B2: 45998 | C2: 78692 | D2: 91279 | E2: 101991 | F2: 155041 | G2: 136700 | H2: 139337 | I2: 164888 | J2: 142381 | K2: 137781 | L2: 191973 | M2: 205489 | N2: 200583 | O2: =SUM(Segment_Q!AL2:AO2) -> 212428.56 | P2: =SUM(Segment_Q!AP2:AS2) -> 225237.22 | Q2: =P2*(1+Q11) -> 243256.2 | R2: =Q2*(1+R11) -> 262716.7 | S2: =R2*(1+S11) -> 283734.03 | T2: =S2*(1+T11) -> 306432.75
A3: Mac | B3: 21783 | C3: 23221 | D3: 21483 | E3: 24079 | F3: 25471 | G3: 22831 | H3: 25569 | I3: 25198 | J3: 25740 | K3: 28622 | L3: 35190 | M3: 40177 | N3: 29357 | O3: =SUM(Segment_Q!AL7:AO7) -> 30021.78 | P3: =SUM(Segment_Q!AP7:AS7) -> 32637.112 | Q3: =P3*(1+Q12) -> 33942.597 | R3: =Q3*(1+R12) -> 35300.301 | S3: =R3*(1+S12) -> 36712.313 | T3: =S3*(1+T12) -> 38180.805
A4: iPad | B4: 19168 | C4: 30945 | D4: 31980 | E4: 30283 | F4: 23227 | G4: 20628 | H4: 18802 | I4: 18380 | J4: 21280 | K4: 23724 | L4: 31862 | M4: 29292 | N4: 28300 | O4: =SUM(Segment_Q!AL12:AO12) -> 25404.559 | P4: =SUM(Segment_Q!AP12:AS12) -> 27553.821 | Q4: =P4*(1+Q13) -> 28655.974 | R4: =Q4*(1+R13) -> 29802.213 | S4: =R4*(1+S13) -> 30994.301 | T4: =S4*(1+T13) -> 32234.073
A5: Wearables, Home and Accessories | H5: 12826 | I5: 17381 | J5: 24482 | K5: 30620 | L5: 38367 | M5: 41241 | N5: 39845 | O5: =SUM(Segment_Q!AL17:AO17) -> 39676.263 | P5: =SUM(Segment_Q!AP17:AS17) -> 48035.271 | Q5: =P5*(1+Q14) -> 52838.799 | R5: =Q5*(1+R14) -> 58122.678 | S5: =R5*(1+S14) -> 63934.946 | T5: =S5*(1+T14) -> 70328.441
A6: Services | B6: 9373 | C6: 12890 | D6: 16051 | E6: 18063 | F6: 19909 | G6: 24348 | H6: 32700 | I6: 39748 | J6: 46291 | K6: 53768 | L6: 68425 | M6: 78129 | N6: 85200 | O6: =SUM(Segment_Q!AL22:AO22) -> 96763.331 | P6: =SUM(Segment_Q!AP22:AS22) -> 112322.31 | Q6: =P6*(1+Q15) -> 130293.88 | R6: =Q6*(1+R15) -> 151140.9 | S6: =R6*(1+S15) -> 175323.44 | T6: =S6*(1+T15) -> 203375.19
A7: Other Products | B7: =7453+4474 -> 11927 | C7: =5615+5145 -> 10760 | D7: 10117 | E7: 8379 | F7: 10067 | G7: 11132
A8: Total Net Sales | B8: =SUM(B2:B7) -> 108249 | C8: =SUM(C2:C7) -> 156508 | D8: =SUM(D2:D7) -> 170910 | E8: =SUM(E2:E7) -> 182795 | F8: =SUM(F2:F7) -> 233715 | G8: =SUM(G2:G7) -> 215639 | H8: =SUM(H2:H7) -> 229234 | I8: =SUM(I2:I7) -> 265595 | ... T8: =SUM(T2:T7) -> 650551.27
A10: YoY
A11: iPhone | C11: =C2/B2-1 -> 0.71077003 | D11: =D2/C2-1 -> 0.15995273 | E11: =E2/D2-1 -> 0.11735448 | F11: =F2/E2-1 -> 0.52014393 | G11: =G2/F2-1 -> -0.11829774 | H11: =H2/G2-1 -> 0.019290417 | I11: =I2/H2-1 -> 0.18337556 | J11: =J2/I2-1 -> -0.13649871 | ... P11: =P2/O2-1 -> 0.060296339 | Q11: =$Q22 -> 0.08 | R11: =$Q22 -> 0.08 | S11: =$Q22 -> 0.08 | T11: =$Q22 -> 0.08
A12: Mac | C12: =C3/B3-1 -> 0.066014782 | D12: =D3/C3-1 -> -0.074846045 | E12: =E3/D3-1 -> 0.12083973 | F12: =F3/E3-1 -> 0.05780971 | G12: =G3/F3-1 -> -0.10364729 | H12: =H3/G3-1 -> 0.11992466 | I12: =I3/H3-1 -> -0.014509758 | J12: =J3/I3-1 -> 0.021509644 | ... P12: =P3/O3-1 -> 0.087114484 | Q12: =$Q23 -> 0.04 | R12: =$Q23 -> 0.04 | S12: =$Q23 -> 0.04 | T12: =$Q23 -> 0.04
A13: iPad | C13: =C4/B4-1 -> 0.61440943 | D13: =D4/C4-1 -> 0.033446437 | E13: =E4/D4-1 -> -0.053064415 | F13: =F4/E4-1 -> -0.23300201 | G13: =G4/F4-1 -> -0.11189564 | H13: =H4/G4-1 -> -0.088520458 | I13: =I4/H4-1 -> -0.022444421 | J13: =J4/I4-1 -> 0.1577802 | ... P13: =P4/O4-1 -> 0.084601419 | Q13: =$Q24 -> 0.04 | R13: =$Q24 -> 0.04 | S13: =$Q24 -> 0.04 | T13: =$Q24 -> 0.04
A14: Wearables, Home and Accessories | C14: N/A | D14: N/A | E14: N/A | F14: N/A | G14: N/A | H14: N/A | I14: =I5/H5-1 -> 0.355138 | J14: =J5/I5-1 -> 0.40854957 | K14: =K5/J5-1 -> 0.25071481 | L14: =L5/K5-1 -> 0.25300457 | M14: =M5/L5-1 -> 0.074908124 | N14: =N5/M5-1 -> -0.03384981 | O14: =O5/N5-1 -> -0.0042348426 | P14: =P5/O5-1 -> 0.21068035 | Q14: =$Q25 -> 0.1 | R14: =$Q25 -> 0.1 | S14: =$Q25 -> 0.1 | T14: =$Q25 -> 0.1
A15: Services | C15: =C6/B6-1 -> 0.37522672 | D15: =D6/C6-1 -> 0.24522886 | E15: =E6/D6-1 -> 0.12535045 | F15: =F6/E6-1 -> 0.10219786 | G15: =G6/F6-1 -> 0.22296449 | H15: =H6/G6-1 -> 0.34302612 | I15: =I6/H6-1 -> 0.21553517 | J15: =J6/I6-1 -> 0.16461206 | ... P15: =P6/O6-1 -> 0.16079415 | Q15: =$Q26 -> 0.16 | R15: =$Q26 -> 0.16 | S15: =$Q26 -> 0.16 | T15: =$Q26 -> 0.16
A16: Other Products | C16: =C7/B7-1 -> -0.097845225 | D16: =D7/C7-1 -> -0.059758364 | E16: =E7/D7-1 -> -0.17179006 | F16: =F7/E7-1 -> 0.20145602 | G16: =G7/F7-1 -> 0.1057912 | H16: N/A | I16: N/A | J16: N/A | K16: N/A | L16: N/A | M16: N/A | N16: N/A | O16: N/A | P16: N/A | V16: Estimate LT Growth Rate
A17: Total Net Sales | C17: =C8/B8-1 -> 0.44581474 | D17: =D8/C8-1 -> 0.092020855 | E17: =E8/D8-1 -> 0.069539524 | F17: =F8/E8-1 -> 0.27856342 | G17: =G8/F8-1 -> -0.077342062 | H17: =H8/G8-1 -> 0.063045182 | I17: =I8/H8-1 -> 0.15861958 | J17: =J8/I8-1 -> -0.020410776 | ... T17: =T8/S8-1 -> 0.10132441 | V17: 0.05
O19: by Segment_Q | P19: by Segment_Q
P21: 5-yr avg | Q21: Our Estimate
O22: iPhone | P22: =AVERAGE(L11:P11) -> 0.11184056 | Q22: 0.08
O23: Mac | P23: =AVERAGE(L12:P12) -> 0.042328219 | Q23: 0.04
O24: iPad | P24: =AVERAGE(L13:P13) -> 0.042158187 | Q24: 0.04
O25: Wearables, Home and Accessories | P25: =AVERAGE(L14:P14) -> 0.10010168 | Q25: 0.1
O26: Services | P26: =AVERAGE(L15:P15) -> 0.16028695 | Q26: 0.16

Sheet DCF
B1: FY2023 | C1: FY2024E | D1: FY2025E | E1: FY2026E | F1: FY2027E | G1: FY2028E | H1: FY2029E | J1: Gross Margin Estimate | M1: Depreciation Expense Calculation | N1: FY2019 | O1: FY2020 | P1: FY2021 | Q1: FY2022 | R1: FY2023
A2: Product Revenue | C2: =SUM(Segment_A!O2:O5) -> 307531.16 | D2: =SUM(Segment_A!P2:P5) -> 333463.43 | E2: =SUM(Segment_A!Q2:Q5) -> 358693.57 | F2: =SUM(Segment_A!R2:R5) -> 385941.89 | G2: =SUM(Segment_A!S2:S5) -> 415375.59 | H2: =SUM(Segment_A!T2:T5) -> 447176.07 | J2: =IS!P33 -> 0.36 | M2: Revenue | N2: =IS!H23 -> 260174 | O2: =IS!I23 -> 274515 | P2: =IS!J23 -> 365817 | Q2: =IS!K23 -> 394328 | R2: =IS!L23 -> 383285
A3: Service Revenue | C3: =Segment_A!O6 -> 96763.331 | D3: =Segment_A!P6 -> 112322.31 | E3: =Segment_A!Q6 -> 130293.88 | F3: =Segment_A!R6 -> 151140.9 | G3: =Segment_A!S6 -> 175323.44 | H3: =Segment_A!T6 -> 203375.19 | J3: =IS!P34 -> 0.71 | M3: Dep & Amort from CFS | N3: =CF!H19 -> 12547 | O3: =CF!I19 -> 11056 | P3: =CF!J19 -> 11284 | Q3: =CF!K19 -> 11104 | R3: =CF!L19 -> 11519 | T3: 5-yr avg
A4: Total Revenue | C4: =SUM(C2:C3) -> 404294.49 | D4: =SUM(D2:D3) -> 445785.74 | E4: =SUM(E2:E3) -> 488987.45 | F4: =SUM(F2:F3) -> 537082.79 | G4: =SUM(G2:G3) -> 590699.03 | H4: =SUM(H2:H3) -> 650551.27 | M4: Dep / Revenue Ratio | N4: =N3/N2 -> 0.048225418 | O4: =O3/O2 -> 0.040274666 | P4: =P3/P2 -> 0.030846024 | Q4: =Q3/Q2 -> 0.028159299 | R4: =R3/R2 -> 0.030053355 | T4: =AVERAGE(N4:R4) -> 0.035511752
A5: Gross Profit | C5: =C2*$J$2+C3*$J$3 -> 179413.18 | D5: =D2*$J$2+D3*$J$3 -> 199795.67 | E5: =E2*$J$2+E3*$J$3 -> 221638.34 | F5: =F2*$J$2+F3*$J$3 -> 246249.12 | G5: =G2*$J$2+G3*$J$3 -> 274014.86 | H5: =H2*$J$2+H3*$J$3 -> 305379.77 | J5: Operating Exp/Revenue
A6: Operating Expense | C6: =C4*$J$6 -> 53899.951 | D6: =D4*$J$6 -> 59431.503 | E6: =E4*$J$6 -> 65191.092 | F6: =F4*$J$6 -> 71603.093 | G6: =G4*$J$6 -> 78751.133 | H6: =H4*$J$6 -> 86730.545 | J6: =IS!P53 -> 0.13331854 | M6: Capex Calculation | N6: FY2019 | O6: FY2020 | P6: FY2021 | Q6: FY2022 | R6: FY2023
A7: Operating Profit | C7: =C5-C6 -> 125513.23 | D7: =D5-D6 -> 140364.17 | E7: =E5-E6 -> 156447.25 | F7: =F5-F6 -> 174646.02 | G7: =G5-G6 -> 195263.72 | H7: =H5-H6 -> 218649.23 | M7: Revenue | N7: =IS!H23 -> 260174 | O7: =IS!I23 -> 274515 | P7: =IS!J23 -> 365817 | Q7: =IS!K23 -> 394328 | R7: =IS!L23 -> 383285
A8: Dep & Amort Expense | C8: =C4*$T$4 -> 14357.206 | D8: =D4*$T$4 -> 15830.633 | E8: =E4*$T$4 -> 17364.801 | F8: =F4*$T$4 -> 19072.751 | G8: =G4*$T$4 -> 20976.758 | H8: =H4*$T$4 -> 23102.216 | M8: Capex from CFS | N8: =CF!H48 -> -10495 | O8: =CF!I48 -> -7309 | P8: =CF!J48 -> -11085 | Q8: =CF!K48 -> -10708 | R8: =CF!L48 -> -10959 | T8: 5-yr avg
A9: Taxable Income | C9: =C7-C8 -> 111156.03 | D9: =D7-D8 -> 124533.54 | E9: =E7-E8 -> 139082.44 | F9: =F7-F8 -> 155573.27 | G9: =G7-G8 -> 174286.97 | H9: =H7-H8 -> 195547.01 | J9: Tax Rate | M9: Capex / Revenue Ratio | N9: =-N8/N7 -> 0.040338389 | O9: =-O8/O7 -> 0.026625139 | P9: =-P8/P7 -> 0.030302036 | Q9: =-Q8/Q7 -> 0.027155059 | R9: =-R8/R7 -> 0.028592301 | T9: =AVERAGE(N9:R9) -> 0.030602585
A10: Tax Expense | C10: =C9*$J$10 -> 16584.012 | D10: =D9*$J$10 -> 18579.88 | E10: =E9*$J$10 -> 20750.516 | F10: =F9*$J$10 -> 23210.879 | G10: =G9*$J$10 -> 26002.883 | H10: =H9*$J$10 -> 29174.792 | J10: =IS!O84 -> 0.1491958
M11: Net Working Capital Calculation | N11: FY2019 | O11: FY2020 | P11: FY2021 | Q11: FY2022 | R11: FY2023
A12: NWC | B12: =R13 -> -51900 | C12: =C4*$T$14 -> -54158.202 | D12: =D4*$T$14 -> -59716.257 | E12: =E4*$T$14 -> -65503.442 | F12: =F4*$T$14 -> -71946.165 | G12: =G4*$T$14 -> -79128.453 | H12: =H4*$T$14 -> -87146.097 | M12: Revenue | N12: =IS!H23 -> 260174 | O12: =IS!I23 -> 274515 | P12: =IS!J23 -> 365817 | Q12: =IS!K23 -> 394328 | R12: =IS!L23 -> 383285
A13: Change in NWC | C13: =C12-B12 -> -2258.2019 | D13: =D12-C12 -> -5558.0554 | E13: =E12-D12 -> -5787.185 | F13: =F12-E12 -> -6442.7222 | G13: =G12-F12 -> -7182.2883 | H13: =H12-G12 -> -8017.644 | M13: Net Working Capital | N13: =BS!H135 -> -33196 | O13: =BS!I135 -> -42389 | P13: =BS!J135 -> -42143 | Q13: =BS!K135 -> -54090 | R13: =BS!L135 -> -51900 | T13: 5-yr avg
M14: NWC / Revenue Ratio | N14: =N13/N12 -> -0.12759153 | O14: =O13/O12 -> -0.15441415 | P14: =P13/P12 -> -0.11520241 | Q14: =Q13/Q12 -> -0.13717007 | R14: =R13/R12 -> -0.13540838 | T14: =AVERAGE(N14:R14) -> -0.13395731
A16: FCF Adjustments
A17: (-)Capex | C17: =C4*$T$9 -> 12372.456 | D17: =D4*$T$9 -> 13642.196 | E17: =E4*$T$9 -> 14964.28 | F17: =F4*$T$9 -> 16436.121 | G17: =G4*$T$9 -> 18076.917 | H17: =H4*$T$9 -> 19908.55
A18: (-) Change in NWC | C18: =C13 -> -2258.2019 | D18: =D13 -> -5558.0554 | E18: =E13 -> -5787.185 | F18: =F13 -> -6442.7222 | G18: =G13 -> -7182.2883 | H18: =H13 -> -8017.644
B20: FY2023 | C20: FY2024E | D20: FY2025E | E20: FY2026E | F20: FY2027E | G20: FY2028E | H20: FY2029E
A21: Year | B21: 0 | C21: 1 | D21: =C21+1 -> 2 | E21: =D21+1 -> 3 | F21: =E21+1 -> 4 | G21: =F21+1 -> 5 | H21: =G21+1 -> 6
A22: Free Cash Flow | C22: =C7-C10-C17-C18 -> 98814.965 | D22: =D7-D10-D17-D18 -> 113700.15 | E22: =E7-E10-E17-E18 -> 126519.63 | F22: =F7-F10-F17-F18 -> 141441.75 | G22: =G7-G10-G17-G18 -> 158366.21 | H22: =H7-H10-H17-H18 -> 177583.53 | J22: WACC | K22: LT Growth
A23: Terminal Value | H23: =H22*(1+K23)/(J23-K23) -> 2864354.8 | J23: =WACC!B17 -> 0.11509763 | K23: =Segment_A!V17 -> 0.05
A24: DCF | C24: =C22/(1+$J$23)^C21 -> 88615.528 | D24: =D22/(1+$J$23)^D21 -> 91439.796 | E24: =E22/(1+$J$23)^E21 -> 91247.138 | F24: =F22/(1+$J$23)^F21 -> 91479.976 | G24: =G22/(1+$J$23)^G21 -> 91853.998 | H24: =(H22+H23)/(1+J23)^H21 -> 1582242.5
A26: Enterprise Value (Sep 30 2023) | B26: =SUM(C24:H24) -> 2036878.9
A27: Enterprise Value (Mar 15 2024) | B27: =B26*((1+J23)^(167/366)) -> 2140687.8
A28: Debt(FY24Q1) | B28: =BS!Q18 -> 106042
A29: Cash(FY24Q1) | B29: =BS!M26 -> 73100
A30: Equity | B30: =B27-B28+B29 -> 2107745.8
A31: Shares Outstanding | B31: =BS!O181 -> 15510.253 | C31: FY24Q1 Diluted
A32: Fair Value | B32: =B30/B31 -> 135.89371
A34: Sensitivity Analysis
C35: LT Growth
B36: =B32 -> 135.89371 | C36: =D36-0.3% -> 0.041 | D36: =E36-0.3% -> 0.044 | E36: =F36-0.3% -> 0.047 | F36: =5% -> 0.05 | G36: =F36+0.3% -> 0.053 | H36: =G36+0.3% -> 0.056 | I36: =H36+0.3% -> 0.059
A37: WACC | B37: =B38-0.3% -> 0.1061 | C37: 140.55698 | D37: 145.93031 | E37: 151.84915 | F37: 158.40102 | G37: 165.69322 | H37: 173.85874 | I37: 183.06444
B38: =B39-0.3% -> 0.1091 | C38: 134.13822 | D38: 138.97819 | E38: 144.28579 | F38: 150.13224 | G38: 156.60397 | H38: 163.80697 | I38: 171.87261
B39: =B40-0.3% -> 0.1121 | C39: 128.26379 | D39: 132.64126 | E39: 137.42219 | F39: 142.66505 | G39: 148.44018 | H39: 154.83296 | I39: 161.9481
B40: 0.1151 | C40: 122.86754 | D40: 126.84162 | E40: 131.16584 | F40: 135.8886 | G40: 141.06768 | H40: 146.77254 | I40: 153.08755
B41: =B40+0.3% -> 0.1181 | C41: 117.89361 | D41: 121.51396 | E41: 125.43982 | F41: 129.71157 | G41: 134.37703 | H41: 139.49326 | I41: 145.12891
B42: =B41+0.3% -> 0.1211 | C42: 113.29452 | D42: 116.60315 | E42: 120.17969 | F42: 124.05804 | G42: 128.2781 | H42: 132.8871 | I42: 137.94142
B43: =B42+0.3% -> 0.1241 | C43: 109.02963 | D43: 112.06233 | E43: 115.33102 | F43: 118.86439 | G43: 122.69594 | H43: 126.86507 | I43: 131.41845

Sheet Multiple Analysis
A6: Company Comparable Analysis > My Apple Inc. Quick Comp (IQ1200533739) > Trading Multiples
A7: Details
A8: Template: | B8: Capital IQ Default Comps
A9: Currency: | B9: US Dollar
A10: As-Of Date: | B10: 45368
A13: Company Comp Set
A14: Company Name | B14: TEV/Total Revenues LTM - Latest | C14: TEV/EBITDA LTM - Latest | D14: TEV/EBIT LTM - Latest | E14: P/Diluted EPS Before Extra LTM - Latest | F14: P/TangBV LTM - Latest | G14: NTM TEV/Forward Total Revenue (Capital IQ) | H14: NTM TEV/Forward EBITDA (Capital IQ) | I14: NTM Forward P/E (Capital IQ)
A15: Advanced Micro Devices, Inc. (NasdaqGS:AMD) | B15: 13.5 | C15: 75.7 | D15: NM | E15: NM | F15: 30.1 | G15: 11.84 | H15: 62.27 | I15: 52.36
A16: Alphabet Inc. (NasdaqGS:GOOGL) | B16: 5.5 | C16: 16.1 | D16: 19.2 | E16: 24.3 | F16: 6.9 | G16: 4.9 | H16: 12 | I16: 20.8
A17: Dell Technologies Inc. (NYSE:DELL) | B17: 1.1 | C17: 15.6 | D17: 18.1 | E17: 24.5 | F17: NM | G17: 1.01 | H17: 8.49 | I17: 14.14
A18: Hewlett Packard Enterprise Company (NYSE:HPE) | B18: 1.1 | C18: 5.9 | D18: 12.1 | E18: 11.5 | F18: 7.6 | G18: 1.06 | H18: 5.62 | I18: 8.88
A19: HP Inc. (NYSE:HPQ) | B19: 0.7 | C19: 6.9 | D19: 8.8 | E19: 8.9 | F19: NM | G19: 0.7 | H19: 7.11 | I19: 8.73
A20: Intel Corporation (NasdaqGS:INTC) | B20: 3.8 | C20: 20.7 | D20: NM | E20: 106.6 | F20: 2.5 | G20: 3.62 | H20: 12.82 | I20: 31.21
A21: Microsoft Corporation (NasdaqGS:MSFT) | B21: 13.7 | C21: 25.7 | D21: 30.8 | E21: 37.6 | F21: 34.6 | G21: 12.01 | H21: 22.86 | I21: 34.15
A22: NetApp, Inc. (NasdaqGS:NTAP) | B22: 3.4 | C22: 13.8 | D22: 17 | E22: 23.3 | F22: NM | G22: 3.23 | H22: 10.82 | I22: 15.39
A23: NVIDIA Corporation (NasdaqGS:NVDA) | B23: 35.2 | C23: 61.8 | D23: 65.1 | E23: 73.6 | F23: 57.8 | G23: 19.42 | H23: 30.6 | I23: 35.62
A24: QUALCOMM Incorporated (NasdaqGS:QCOM) | B24: 5.2 | C24: 17.2 | D24: 21.1 | E24: 23.9 | F24: 17.1 | G24: 4.92 | H24: 12.96 | I24: 17.14
A25: Samsung Electronics Co., Ltd. (KOSE:A005930) | B25: 1.6 | C25: 9 | D25: 55.5 | E25: 33.9 | F25: 1.5 | G25: 1.37 | H25: 5.46 | I25: 16.63
A27: Summary Statistics | B27: TEV/Total Revenues LTM - Latest | C27: TEV/EBITDA LTM - Latest | D27: TEV/EBIT LTM - Latest | E27: P/Diluted EPS Before Extra LTM - Latest | F27: P/TangBV LTM - Latest | G27: NTM TEV/Forward Total Revenue (Capital IQ) | H27: NTM TEV/Forward EBITDA (Capital IQ) | I27: NTM Forward P/E (Capital IQ)
A28: High | B28: 35.2 | C28: 75.7 | D28: 65.1 | E28: 106.6 | F28: 57.8 | G28: 19.42 | H28: 62.27 | I28: 52.36
A29: Low | B29: 0.7 | C29: 5.9 | D29: 8.8 | E29: 8.9 | F29: 1.5 | G29: 0.7 | H29: 5.46 | I29: 8.73
A30: Mean | B30: 7.7 | C30: 24.4 | D30: 27.5 | E30: 36.8 | F30: 19.8 | G30: 5.83 | H30: 17.36 | I30: 23.19
A31: Median | B31: 3.8 | C31: 16.1 | D31: 19.2 | E31: 24.4 | F31: 12.4 | G31: 3.62 | H31: 12 | I31: 17.14
A34: Displaying 11 Companies.
A37: Excel Comp Set ID: IQ1200533739
A39: Values converted at today's spot rate.
A41: Since the market usually uses PE to evaluate stock price, we chose Mean NTM PE of these companies: 23.19, with Consensus NTM EPS of 6.68
B42: CIQ Consensus NTM EPS | C42: Peers Trailing PE | D42: Price by PE
A43: PE Stock Price | B43: =6.68 -> 6.68 | C43: =I30 -> 23.19 | D43: =B43*C43 -> 154.9092
A48: Historical Equity Pricing Data supplied by Interactive Data Pricing and Reference Data LLC

Sheet Geo_Segments
A5: Apple Inc. (NasdaqGS:AAPL) > Financials > Segments
A7: In Millions of the reported currency. | B7: View By: | C7: Line Items | E7: Restatement: | F7: Latest Filings
B8: Period Type: | C8: Annual | E8: Order: | F8: Latest on Right
B9: Currency: | C9: Reported Currency | E9: Conversion: | F9: Historical
B10: Units: | C10: S&P Capital IQ (Default) | E10: Decimals: | F10: Capital IQ (Default)
A13: Business Segments
A14: For the Fiscal Period Ending | B14: 12 months Sep-28-2013 | C14: 12 months Sep-27-2014 | D14: 12 months Sep-26-2015 | E14: 12 months Sep-24-2016 | F14: 12 months Sep-30-2017 | G14: 12 months Sep-29-2018 | H14: 12 months Sep-28-2019 | I14: 12 months Sep-26-2020 | J14: 12 months Sep-25-2021 | K14: 12 months Sep-24-2022 | L14: 12 months Sep-30-2023
A15: Currency | B15: USD | C15: USD | D15: USD | E15: USD | F15: USD | G15: USD | H15: USD | I15: USD | J15: USD | K15: USD | L15: USD
A16: Revenues
A17: Americas | B17: 77093 | C17: 80095 | D17: 93864 | E17: 86613 | F17: 96600 | G17: 112093 | H17: 116914 | I17: 124556 | J17: 153306 | K17: 169658 | L17: 162560
A18: Europe | B18: 40980 | C18: 44285 | D18: 50337 | E18: 49952 | F18: 54938 | G18: 62420 | H18: 60288 | I18: 68640 | J18: 89307 | K18: 95118 | L18: 94294
A19: Greater China | B19: 27016 | C19: 31853 | D19: 58715 | E19: 48492 | F19: 44764 | G19: 51942 | H19: 43678 | I19: 40308 | J19: 68366 | K19: 74200 | L19: 72559
A20: Japan | B20: 13782 | C20: 15314 | D20: 15706 | E20: 16928 | F20: 17733 | G20: 21733 | H20: 21506 | I20: 21418 | J20: 28482 | K20: 25977 | L20: 24257
A21: Rest of Asia Pacific | B21: 12039 | C21: 11248 | D21: 15093 | E21: 13654 | F21: 15199 | G21: 17407 | H21: 17788 | I21: 19593 | J21: 26356 | K21: 29375 | L21: 29615
A22: Total Revenues | B22: 170910 | C22: 182795 | D22: 233715 | E22: 215639 | F22: 229234 | G22: 265595 | H22: 260174 | I22: 274515 | J22: 365817 | K22: 394328 | L22: 383285
A24: Operating Profit Before Tax
A25: Americas | B25: 24829 | C25: 26158 | D25: 31186 | E25: 28172 | F25: 30684 | G25: 34864 | H25: 35099 | I25: 37722 | J25: 53382 | K25: 62683 | L25: 60508
A26: Europe | B26: 12767 | C26: 14434 | D26: 16527 | E26: 15348 | F26: 16514 | G26: 19955 | H26: 19195 | I26: 22170 | J26: 32505 | K26: 35233 | L26: 36098
A27: Greater China | B27: 8499 | C27: 11039 | D27: 23002 | E27: 18835 | F27: 17032 | G27: 19742 | H27: 16232 | I27: 15261 | J27: 28504 | K27: 31153 | L27: 30328
A28: Japan | B28: 6668 | C28: 6904 | D28: 7617 | E28: 7165 | F28: 8097 | G28: 9500 | H28: 9369 | I28: 9279 | J28: 12798 | K28: 12257 | L28: 11888
A29: Rest of Asia Pacific | B29: 3762 | C29: 3674 | D29: 5518 | E29: 4781 | F29: 5304 | G29: 6181 | H29: 6055 | I29: 6808 | J29: 9817 | K29: 11569 | L29: 12066
A30: Unallocated Research and Development Expense | B30: -4475 | C30: -6041 | D30: -8067 | E30: -10045 | F30: -11581 | G30: -14236 | H30: -16217 | I30: -18752 | J30: -21914 | K30: -26251 | L30: -29915
A31: Other Corporate Expenses, Net | B31: -3051 | C31: -3665 | D31: -4553 | E31: -4232 | F31: -4706 | G31: -5108 | H31: -5803 | I31: -6200 | J31: -6143 | K31: -7207 | L31: -6672
A32: Total Operating Profit Before Tax | B32: 48999 | C32: 52503 | D32: 71230 | E32: 60024 | F32: 61344 | G32: 70898 | H32: 63930 | I32: 66288 | J32: 108949 | K32: 119437 | L32: 114301
A34: Assets
A35: Americas | B35: 5653 | C35: - | D35: - | E35: - | F35: - | G35: - | H35: - | I35: - | J35: - | K35: - | L35: -
A36: Europe | B36: 3134 | C36: - | D36: - | E36: - | F36: - | G36: - | H36: - | I36: - | J36: - | K36: - | L36: -
A37: Greater China | B37: 2943 | C37: - | D37: - | E37: - | F37: - | G37: - | H37: - | I37: - | J37: - | K37: - | L37: -
A38: Japan | B38: 2932 | C38: - | D38: - | E38: - | F38: - | G38: - | H38: - | I38: - | J38: - | K38: - | L38: -
A39: Rest of Asia Pacific | B39: 923 | C39: - | D39: - | E39: - | F39: - | G39: - | H39: - | I39: - | J39: - | K39: - | L39: -
A40: Retail | B40: 3329 | C40: - | D40: - | E40: - | F40: - | G40: - | H40: - | I40: - | J40: - | K40: - | L40: -
A41: Corporate Assets | B41: 188086 | C41: - | D41: - | E41: - | F41: - | G41: - | H41: - | I41: - | J41: - | K41: - | L41: -
A42: Total Assets | B42: 207000 | C42: - | D42: - | E42: - | F42: - | G42: - | H42: - | I42: - | J42: - | K42: - | L42: -
A45: Filing Date | B45: 42305 | C45: 42669 | D45: 43042 | E45: 43409 | F45: 43769 | G45: 44134 | H45: 44498 | I45: 44862 | J45: 45233 | K45: 45233 | L45: 45233
A48: Geographic Segments
A49: For the Fiscal Period Ending | B49: 12 months Sep-28-2013 | C49: 12 months Sep-27-2014 | D49: 12 months Sep-26-2015 | E49: 12 months Sep-24-2016 | F49: 12 months Sep-30-2017 | G49: 12 months Sep-29-2018 | H49: 12 months Sep-28-2019 | I49: 12 months Sep-26-2020 | J49: 12 months Sep-25-2021 | K49: 12 months Sep-24-2022 | L49: 12 months Sep-30-2023
A50: Currency | B50: USD | C50: USD | D50: USD | E50: USD | F50: USD | G50: USD | H50: USD | I50: USD | J50: USD | K50: USD | L50: USD
A51: Revenues
A52: Greater China | B52: 25946 | C52: 30638 | D52: 58715 | E52: 48492 | F52: 44764 | G52: 51942 | H52: 43678 | I52: 40308 | J52: 68366 | K52: 74200 | L52: 72559
A53: United States (U.S.) | B53: 66197 | C53: 68909 | D53: 81732 | E53: 75667 | F53: 84339 | G53: 98061 | H53: 102266 | I53: 109197 | J53: 133803 | K53: 147859 | L53: 138573
A54: Other Countries | B54: 78767 | C54: 83248 | D54: 93268 | E54: 91480 | F54: 100131 | G54: 115592 | H54: 114230 | I54: 125010 | J54: 163648 | K54: 172269 | L54: 172153
A55: Total Revenues | B55: 170910 | C55: 182795 | D55: 233715 | E55: 215639 | F55: 229234 | G55: 265595 | H55: 260174 | I55: 274515 | J55: 365817 | K55: 394328 | L55: 383285
A57: Assets
A58: Greater China | B58: 7403 | C58: 9477 | D58: 8722 | E58: 7875 | F58: 10211 | G58: 13268 | H58: 9064 | I58: 7256 | J58: 7521 | K58: 7260 | L58: 5778
A59: United States (U.S.) | B59: 7399 | C59: 9108 | D59: 12022 | E59: 16364 | F59: 20637 | G59: 23963 | H59: 24711 | I59: 25890 | J59: 28203 | K59: 31119 | L59: 33276
A60: Other Countries | B60: 2786 | C60: 2917 | D60: 3040 | E60: 2771 | F60: 2935 | G60: 4073 | H60: 3603 | I60: 3620 | J60: 3716 | K60: 3738 | L60: 4661
A61: Total Assets | B61: 17588 | C61: 21502 | D61: 23784 | E61: 27010 | F61: 33783 | G61: 41304 | H61: 37378 | I61: 36766 | J61: 39440 | K61: 42117 | L61: 43715
A64: Filing Date | B64: 42305 | C64: 42669 | D64: 43042 | E64: 43409 | F64: 43769 | G64: 44134 | H64: 44498 | I64: 44862 | J64: 45233 | K64: 45233 | L64: 45233
